Workbook

Sheet Summary
A1: APX vetting scenarios by module
A2: Private. Built from test-scenarios/apx-*.md against APX v0.11.0 (LPR re-vetted against v0.12.1 on 2026-09-28). Each module has its own tab; counts below are formulas over those tabs.
A4: Module | B4: OpenAPI tags | C4: Scenarios | D4: Happy | E4: Refusal | F4: Lifecycle | G4: Security | H4: Edge | I4: Exchanges | J4: With open gap
A5: apx-accounts | B5: Accounts | C5: =COUNTA('apx-accounts'!A:A)-1 | D5: =COUNTIF('apx-accounts'!C:C,"happy") | E5: =COUNTIF('apx-accounts'!C:C,"refusal") | F5: =COUNTIF('apx-accounts'!C:C,"lifecycle") | G5: =COUNTIF('apx-accounts'!C:C,"security") | H5: =COUNTIF('apx-accounts'!C:C,"edge") | I5: =SUM('apx-accounts'!G:G) | J5: =COUNTIF('apx-accounts'!H:H,"?*")
A6: apx-alerts | B6: Alerts | C6: =COUNTA('apx-alerts'!A:A)-1 | D6: =COUNTIF('apx-alerts'!C:C,"happy") | E6: =COUNTIF('apx-alerts'!C:C,"refusal") | F6: =COUNTIF('apx-alerts'!C:C,"lifecycle") | G6: =COUNTIF('apx-alerts'!C:C,"security") | H6: =COUNTIF('apx-alerts'!C:C,"edge") | I6: =SUM('apx-alerts'!G:G) | J6: =COUNTIF('apx-alerts'!H:H,"?*")
A7: apx-control | B7: Control | C7: =COUNTA('apx-control'!A:A)-1 | D7: =COUNTIF('apx-control'!C:C,"happy") | E7: =COUNTIF('apx-control'!C:C,"refusal") | F7: =COUNTIF('apx-control'!C:C,"lifecycle") | G7: =COUNTIF('apx-control'!C:C,"security") | H7: =COUNTIF('apx-control'!C:C,"edge") | I7: =SUM('apx-control'!G:G) | J7: =COUNTIF('apx-control'!H:H,"?*")
A8: apx-credentials | B8: Credentials | C8: =COUNTA('apx-credentials'!A:A)-1 | D8: =COUNTIF('apx-credentials'!C:C,"happy") | E8: =COUNTIF('apx-credentials'!C:C,"refusal") | F8: =COUNTIF('apx-credentials'!C:C,"lifecycle") | G8: =COUNTIF('apx-credentials'!C:C,"security") | H8: =COUNTIF('apx-credentials'!C:C,"edge") | I8: =SUM('apx-credentials'!G:G) | J8: =COUNTIF('apx-credentials'!H:H,"?*")
A9: apx-data | B9: Data, Places, Sessions, Rate Tables, Assigned Rights, Right Specifications, Observation, Organisations, Quote | C9: =COUNTA('apx-data'!A:A)-1 | D9: =COUNTIF('apx-data'!C:C,"happy") | E9: =COUNTIF('apx-data'!C:C,"refusal") | F9: =COUNTIF('apx-data'!C:C,"lifecycle") | G9: =COUNTIF('apx-data'!C:C,"security") | H9: =COUNTIF('apx-data'!C:C,"edge") | I9: =SUM('apx-data'!G:G) | J9: =COUNTIF('apx-data'!H:H,"?*")
A10: apx-discovery | B10: Discovery | C10: =COUNTA('apx-discovery'!A:A)-1 | D10: =COUNTIF('apx-discovery'!C:C,"happy") | E10: =COUNTIF('apx-discovery'!C:C,"refusal") | F10: =COUNTIF('apx-discovery'!C:C,"lifecycle") | G10: =COUNTIF('apx-discovery'!C:C,"security") | H10: =COUNTIF('apx-discovery'!C:C,"edge") | I10: =SUM('apx-discovery'!G:G) | J10: =COUNTIF('apx-discovery'!H:H,"?*")
A11: apx-events | B11: Subscription | C11: =COUNTA('apx-events'!A:A)-1 | D11: =COUNTIF('apx-events'!C:C,"happy") | E11: =COUNTIF('apx-events'!C:C,"refusal") | F11: =COUNTIF('apx-events'!C:C,"lifecycle") | G11: =COUNTIF('apx-events'!C:C,"security") | H11: =COUNTIF('apx-events'!C:C,"edge") | I11: =SUM('apx-events'!G:G) | J11: =COUNTIF('apx-events'!H:H,"?*")
A12: apx-lpr | B12: LPR | C12: =COUNTA('apx-lpr'!A:A)-1 | D12: =COUNTIF('apx-lpr'!C:C,"happy") | E12: =COUNTIF('apx-lpr'!C:C,"refusal") | F12: =COUNTIF('apx-lpr'!C:C,"lifecycle") | G12: =COUNTIF('apx-lpr'!C:C,"security") | H12: =COUNTIF('apx-lpr'!C:C,"edge") | I12: =SUM('apx-lpr'!G:G) | J12: =COUNTIF('apx-lpr'!H:H,"?*")
A13: apx-permits | B13: Permits | C13: =COUNTA('apx-permits'!A:A)-1 | D13: =COUNTIF('apx-permits'!C:C,"happy") | E13: =COUNTIF('apx-permits'!C:C,"refusal") | F13: =COUNTIF('apx-permits'!C:C,"lifecycle") | G13: =COUNTIF('apx-permits'!C:C,"security") | H13: =COUNTIF('apx-permits'!C:C,"edge") | I13: =SUM('apx-permits'!G:G) | J13: =COUNTIF('apx-permits'!H:H,"?*")
A14: apx-reservations | B14: Reservations | C14: =COUNTA('apx-reservations'!A:A)-1 | D14: =COUNTIF('apx-reservations'!C:C,"happy") | E14: =COUNTIF('apx-reservations'!C:C,"refusal") | F14: =COUNTIF('apx-reservations'!C:C,"lifecycle") | G14: =COUNTIF('apx-reservations'!C:C,"security") | H14: =COUNTIF('apx-reservations'!C:C,"edge") | I14: =SUM('apx-reservations'!G:G) | J14: =COUNTIF('apx-reservations'!H:H,"?*")
A15: apx-resolution | B15: Resolution, Support | C15: =COUNTA('apx-resolution'!A:A)-1 | D15: =COUNTIF('apx-resolution'!C:C,"happy") | E15: =COUNTIF('apx-resolution'!C:C,"refusal") | F15: =COUNTIF('apx-resolution'!C:C,"lifecycle") | G15: =COUNTIF('apx-resolution'!C:C,"security") | H15: =COUNTIF('apx-resolution'!C:C,"edge") | I15: =SUM('apx-resolution'!G:G) | J15: =COUNTIF('apx-resolution'!H:H,"?*")
A16: apx-tolling | B16: Tolling | C16: =COUNTA('apx-tolling'!A:A)-1 | D16: =COUNTIF('apx-tolling'!C:C,"happy") | E16: =COUNTIF('apx-tolling'!C:C,"refusal") | F16: =COUNTIF('apx-tolling'!C:C,"lifecycle") | G16: =COUNTIF('apx-tolling'!C:C,"security") | H16: =COUNTIF('apx-tolling'!C:C,"edge") | I16: =SUM('apx-tolling'!G:G) | J16: =COUNTIF('apx-tolling'!H:H,"?*")
A17: apx-valet | B17: Valet | C17: =COUNTA('apx-valet'!A:A)-1 | D17: =COUNTIF('apx-valet'!C:C,"happy") | E17: =COUNTIF('apx-valet'!C:C,"refusal") | F17: =COUNTIF('apx-valet'!C:C,"lifecycle") | G17: =COUNTIF('apx-valet'!C:C,"security") | H17: =COUNTIF('apx-valet'!C:C,"edge") | I17: =SUM('apx-valet'!G:G) | J17: =COUNTIF('apx-valet'!H:H,"?*")
A18: apx-validations | B18: Validations | C18: =COUNTA('apx-validations'!A:A)-1 | D18: =COUNTIF('apx-validations'!C:C,"happy") | E18: =COUNTIF('apx-validations'!C:C,"refusal") | F18: =COUNTIF('apx-validations'!C:C,"lifecycle") | G18: =COUNTIF('apx-validations'!C:C,"security") | H18: =COUNTIF('apx-validations'!C:C,"edge") | I18: =SUM('apx-validations'!G:G) | J18: =COUNTIF('apx-validations'!H:H,"?*")
A19: apx-violations | B19: Violations | C19: =COUNTA('apx-violations'!A:A)-1 | D19: =COUNTIF('apx-violations'!C:C,"happy") | E19: =COUNTIF('apx-violations'!C:C,"refusal") | F19: =COUNTIF('apx-violations'!C:C,"lifecycle") | G19: =COUNTIF('apx-violations'!C:C,"security") | H19: =COUNTIF('apx-violations'!C:C,"edge") | I19: =SUM('apx-violations'!G:G) | J19: =COUNTIF('apx-violations'!H:H,"?*")
A20: Total | C20: =SUM(C5:C19) | D20: =SUM(D5:D19) | E20: =SUM(E5:E19) | F20: =SUM(F5:F19) | G20: =SUM(G5:G19) | H20: =SUM(H5:H19) | I20: =SUM(I5:I19) | J20: =SUM(J5:J19)
A22: Kinds: happy = the intended path; refusal = the server correctly says no; lifecycle = a state machine walked through its transitions; security = scopes, grants, tokens; edge = retries, limits, and unusual inputs. 'With open gap' counts scenarios still citing an unfixed spec finding (F-RSV-02, an upstream APDS defect with no additive workaround).

Sheet apx-accounts
A1: ID | B1: Title | C1: Kind | D1: Annex A rows | E1: Scenario (Given / When / Then) | F1: Exchanges (request → status) | G1: Exchange count | H1: Open spec gap
A2: ACC-01 | B2: A monthly parker calls in: lookup by phone | C2: happy | D2: APX-ACC-01 | E2: Given J. Smith calls the operator's number from the phone on file. When the console looks the caller up by phone before the agent answers. Then 200 with one account, its balance and status, and the place it is valid at, so the greeting can be "Hi J., I see $185 owing at Lakeside". | F2: GET /v1/accounts → 200 | G2: =IF(F2="",0,LEN(F2)-LEN(SUBSTITUTE(F2,CHAR(10),""))+1)
A3: ACC-02 | B3: Every other key: plate, card, name, a combination, by id, and the ones that are not there | C3: happy | D3: APX-ACC-01 | E3: Given callers who know only their plate, only their access card, or only their name. When the console tries each filter, then narrows a common surname with a plate, then fetches by id. Then each lookup returns the matching accounts, an unknown plate returns an empty list, and an unknown id is 404. The email key and the §13.5(3) place narrowing are declared (F-ACC-09, F-ACC-08 fixed), and Account.email comes back under apx.accounts:read. | F3: GET /v1/accounts → 200 GET /v1/accounts → 200 GET /v1/accounts → 200 GET /v1/accounts → 200 GET /v1/accounts/c2000000-0000-4000-8000-000000000004 → 200 GET /v1/accounts/c2000000-0000-4000-8000-0000000000ff → 404 GET /v1/accounts → 200 GET /v1/accounts → 200 GET /v1/accounts → 200 | G3: =IF(F3="",0,LEN(F3)-LEN(SUBSTITUTE(F3,CHAR(10),""))+1)
A4: ACC-03 | B4: The grant, not the scope, bounds a place-less lookup | C4: security | D4: APX-ACC-01, APX-CORE-07, APX-CORE-08 | E4: Given J. Smith holds accounts at both Lakeside and Harbor Deck under the same plate. When a token granted only Lakeside searches the plate, an all-places token searches it, and a token with no apx_places claim searches it. Then the first sees only the Lakeside account, the second sees both, and the third sees nothing (fail-closed; whether that is an empty 200 or a 403 is F-ACC-13). Fetching the Harbor account by id with the Lakeside token is 403 insufficient-grant, which the operation does not declare (F-ACC-02). | F4: GET /v1/accounts → 200 GET /v1/accounts → 200 GET /v1/accounts → 200 GET /v1/accounts/c2000000-0000-4000-8000-000000000006 → 403 | G4: =IF(F4="",0,LEN(F4)-LEN(SUBSTITUTE(F4,CHAR(10),""))+1)
A5: ACC-04 | B5: The wrong scope on every route | C5: refusal | D5: APX-CORE-07 | E5: Given a payments-only token (apx.payments:write) and a read-only token (apx.accounts:read). When the payments token reads accounts and payment history, and the read token takes a payment and voids one. Then each is 403 insufficient-scope; nothing is read or moved. | F5: GET /v1/accounts → 403 GET /v1/payments → 403 POST /v1/payments → 403 POST /v1/payments/e8000000-0000-4000-8000-000000000205/void → 403 | G5: =IF(F5="",0,LEN(F5)-LEN(SUBSTITUTE(F5,CHAR(10),""))+1)
A6: ACC-05 | B6: Pay the balance over the IVR; the balance drops; the event lands | C6: happy | D6: APX-ACC-02, APX-ACC-03 | E6: Given J. Smith agrees to pay the $185.00 and is transferred to the PCI-compliant IVR, which captures the card out of band. When the console records the payment with method: autoAttendant and an idempotency key. Then 201 with a PaymentRecord bound to Lakeside, carrying a transactionID and only the last four digits; the account re-read shows a zero balance and a bumped version; and apx.accounts.payment.recorded.v1 is published with the record as data. | F6: POST /v1/payments → 201 GET /v1/accounts/c2000000-0000-4000-8000-000000000004 → 200 | G6: =IF(F6="",0,LEN(F6)-LEN(SUBSTITUTE(F6,CHAR(10),""))+1)
A7: ACC-06 | B7: The IVR bridge retries: same key, same body | C7: edge | D7: APX-ACC-02 | E7: Given the 201 from ACC-05 was lost between the IVR bridge and the console. When the bridge retries with the identical key and body. Then 200 with the ORIGINAL record; J. Smith is not charged twice and the balance stays at zero. | F7: POST /v1/payments → 200 | G7: =IF(F7="",0,LEN(F7)-LEN(SUBSTITUTE(F7,CHAR(10),""))+1)
A8: ACC-07 | B8: Same key with a different amount; no key; nothing to settle | C8: refusal | D8: APX-ACC-02, APX-CORE-05 | E8: Given three broken clients. When one reuses cc-8101-pay for a different amount, one omits Idempotency-Key, and one sends a place and an amount with neither account nor ticketNumber. Then 409 idempotency-conflict, 400 idempotency-key-required, and a 400 the operation describes ("no account/ticket to settle") but Part 12 has no slug for (F-ACC-03). | F8: POST /v1/payments → 409 POST /v1/payments → 400 POST /v1/payments → 400 | G8: =IF(F8="",0,LEN(F8)-LEN(SUBSTITUTE(F8,CHAR(10),""))+1)
A9: ACC-08 | B9: Declined at the exit lane, and the decline is a record too | C9: refusal | D9: APX-ACC-02, APX-ACC-03 | E9: Given the transient parker on ticket T-61077 reads a card to the agent after the lane terminal declined it twice. When the agent takes $18.00 by card. Then 422 payment-declined; the declined attempt is nonetheless recorded (it is what the resolution context's payments[] overlay shows) and published on apx.accounts.payment.recorded.v1 with paymentStatus: declined. The problem body points at that record through the payment extension member §13.1 now names (F-ACC-11 fixed). | F9: POST /v1/payments → 422 | G9: =IF(F9="",0,LEN(F9)-LEN(SUBSTITUTE(F9,CHAR(10),""))+1)
A10: ACC-09 | B10: A ticket payment with the accounting write-back | C10: happy | D10: APX-ACC-02, APX-ACC-03 | E10: Given the lost-ticket parker from scenario 04 owes $4.50 more on T-1001. When the agent takes it by card and then posts the payment to PARIS. Then 201 with the PaymentRecord, 201 with the Posting (a ticket payment updates no account, so accountUpdated is false), and a posting against a payment id that never existed is 404. | F10: POST /v1/payments → 201 POST /v1/payments/e8000000-0000-4000-8000-000000000202/postings → 201 POST /v1/payments/e8000000-0000-4000-8000-0000000000ff/postings → 404 POST /v1/payments/e8000000-0000-4000-8000-000000000201/postings → 201 | G10: =IF(F10="",0,LEN(F10)-LEN(SUBSTITUTE(F10,CHAR(10),""))+1)
A11: ACC-10 | B11: Posting a declined payment | C11: refusal | D11: APX-ACC-02, APX-ACC-05 | E11: Given a reconciliation script that posts every PaymentRecord it sees. When it posts the declined attempt from ACC-08. Then 409 payment-state-illegal: nothing was collected, and only an approved payment can be posted (§13.1a; F-ACC-04 fixed). | F11: POST /v1/payments/e8000000-0000-4000-8000-000000000203/postings → 409 | G11: =IF(F11="",0,LEN(F11)-LEN(SUBSTITUTE(F11,CHAR(10),""))+1)
A12: ACC-11 | B12: Declined at the exit: the payment link of first resort | C12: happy | D12: APX-ACC-04, APX-ACC-03 | E12: Given the resolution context for T-61077 lists "send payment link" as the allowed action and vending the gate as not allowed. When the agent sends an SMS link with no amount (charge the current amount due). Then 201 with the link in sent; GET /v1/payment-links/{id} shows it opened; a replay of the same key returns the link in its current representation (Part 4 §4.2a); the driver pays with a different card and the payment arrives on apx.accounts.payment.recorded.v1 (F-ACC-06 fixed). | F12: POST /v1/payment-links → 201 GET /v1/payment-links/e6000000-0000-4000-8000-000000000052 → 200 POST /v1/payment-links → 200 | G12: =IF(F12="",0,LEN(F12)-LEN(SUBSTITUTE(F12,CHAR(10),""))+1)
A13: ACC-12 | B13: Payment-link refusals | C13: refusal | D13: APX-ACC-04, APX-CORE-05 | E13: Given three more broken clients. When one sends a link with no account, ticket, or session; one asks for channel fax; and one reuses ctx-e5000000-0012-paylink for a different ticket. Then 400 invalid-request for nothing to settle, 422 request-unprocessable for the channel (§13.1a; F-ACC-03 fixed), and 409 idempotency-conflict. | F13: POST /v1/payment-links → 400 POST /v1/payment-links → 422 POST /v1/payment-links → 409 | G13: =IF(F13="",0,LEN(F13)-LEN(SUBSTITUTE(F13,CHAR(10),""))+1)
... A27: ACC-26 | B27: The shared responses on the remaining routes | C27: edge | D27: APX-CORE-05, APX-CORE-06, APX-CORE-07 | E27: Given the console from ACC-23 (rate-limited), ACC-24 (expired token), and a read-only reporting token (apx.accounts:read only). When each hits the routes the earlier scenarios did not. Then the shared 401, 403, 429, and 400 responses every secured operation declares (Part 12 §12.3). | F27: GET /v1/accounts/c2000000-0000-4000-8000-000000000004 → 401 GET /v1/accounts/c2000000-0000-4000-8000-000000000004 → 429 POST /v1/payments/e8000000-0000-4000-8000-000000000201/postings → 401 POST /v1/payments/e8000000-0000-4000-8000-000000000201/postings → 403 POST /v1/payments/e8000000-0000-4000-8000-000000000201/postings → 429 POST /v1/payments/e8000000-0000-4000-8000-000000000201/postings → 400 POST /v1/payments/e8000000-0000-4000-8000-000000000206/void → 400 POST /v1/payments/e8000000-0000-4000-8000-000000000205/capture → 400 GET /v1/payment-links/e6000000-0000-4000-8000-000000000303 → 401 GET /v1/payment-links/e6000000-0000-4000-8000-000000000303 → 429 POST /v1/payment-links/e6000000-0000-4000-8000-000000000304/cancel → 401 POST /v1/payment-links/e6000000-0000-4000-8000-000000000304/cancel → 429 | G27: =IF(F27="",0,LEN(F27)-LEN(SUBSTITUTE(F27,CHAR(10),""))+1)

Sheet apx-alerts
A1: ID | B1: Title | C1: Kind | D1: Annex A rows | E1: Scenario (Given / When / Then) | F1: Exchanges (request → status) | G1: Exchange count | H1: Open spec gap
A2: ALT-01 | B2: The intercom is pressed at exit lane 2 | C2: happy | D2: APX-ALT-02, APX-ALT-03 | E2: Given a driver presses the intercom at exit lane 2 and the lane controller integrates with the alert plane. When it raises an intercomRequest with an idempotency key, the intercom as source.device and the lane as source.place. Then 201 with the full alert in raised, one history entry, provenance in recordInfo; subscribers receive apx.alert.raised.v1 with the same alert as data; and a read by id returns it unchanged. | F2: POST /v1/alerts → 201 GET /v1/alerts/e7000000-0000-4000-8000-000000000701 → 200 | G2: =IF(F2="",0,LEN(F2)-LEN(SUBSTITUTE(F2,CHAR(10),""))+1)
A3: ALT-02 | B3: The lane controller retries: same key, same body, before and after acknowledgement | C3: edge | D3: APX-ALT-02, APX-ALT-01 | E3: Given the 201 from ALT-01 never reached the lane controller. When it replays the identical key and body; the agent then picks up the intercom and acknowledges; and a late duplicate arrives after that. Then the first replay is 200 with the original alert, the acknowledgement is 200 at version 2, and the late replay is 200 again — no second alert exists. The late replay returns the alert as it now stands, acknowledged at version 2 (Part 4 §4.2a, Part 7 §7.2; F-ALT-09 fixed). | F3: POST /v1/alerts → 200 POST /v1/alerts/e7000000-0000-4000-8000-000000000701/acknowledge → 200 POST /v1/alerts → 200 | G3: =IF(F3="",0,LEN(F3)-LEN(SUBSTITUTE(F3,CHAR(10),""))+1)
A4: ALT-03 | B4: Same key, different body; and no key at all | C4: refusal | D4: APX-ALT-02, APX-CORE-05 | E4: Given a firmware bug reuses the intercom key for a second press on the entry lane, and a second device omits the header entirely. When both POST. Then 409 idempotency-conflict for the reused key and 400 idempotency-key-required for the missing one; neither raises anything. | F4: POST /v1/alerts → 409 POST /v1/alerts → 400 | G4: =IF(F4="",0,LEN(F4)-LEN(SUBSTITUTE(F4,CHAR(10),""))+1)
A5: ALT-04 | B5: Alerts the schema refuses: a made-up severity, no detection time | C5: refusal | D5: APX-ALT-03, APX-CORE-05 | E5: Given two integrators reading the schema loosely. When one sends severity: urgent (severity is CLOSED) and one omits detectionTime. Then both are 400 invalid-request, with errors[] naming the field (Part 12 §12.4; F-ALT-05 fixed). | F5: POST /v1/alerts → 400 POST /v1/alerts → 400 | G5: =IF(F5="",0,LEN(F5)-LEN(SUBSTITUTE(F5,CHAR(10),""))+1)
A6: ALT-05 | B6: Pay station 3 faults: auto-raised, acknowledged, resolved | C6: lifecycle | D6: APX-ALT-01, APX-ALT-03 | E6: Given pay station 3 transitions to fault on the Control plane (Part 6 §6.4 says that SHOULD auto-raise a deviceFault). When the server raises it, the agent acknowledges it, and the field tech resolves it two hours later. Then subscribers see one apx.alert.raised.v1 and two apx.alert.status.v1 events, version climbs 1 → 2 → 3, and the history is only ever appended to. No client POSTed the raise. | F6: POST /v1/alerts/e7000000-0000-4000-8000-000000000702/acknowledge → 200 POST /v1/alerts/e7000000-0000-4000-8000-000000000702/resolve → 200 | G6: =IF(F6="",0,LEN(F6)-LEN(SUBSTITUTE(F6,CHAR(10),""))+1)
A7: ALT-06 | B7: Lane blocked and cleared on the spot: raised straight to resolved | C7: lifecycle | D7: APX-ALT-01 | E7: Given a stalled car in exit lane 2 and an attendant already walking over. When the lane raises laneBlocked at critical and, four minutes later, the attendant resolves it without anyone having acknowledged. Then 201, then 200 in resolved at version 2 with a two-entry history. Part 7 §7.3 permits raised → resolved directly; no acknowledgement is required. | F7: POST /v1/alerts → 201 POST /v1/alerts/e7000000-0000-4000-8000-000000000703/resolve → 200 | G7: =IF(F7="",0,LEN(F7)-LEN(SUBSTITUTE(F7,CHAR(10),""))+1)
A8: ALT-07 | B8: Transitions the state machine forbids | C8: refusal | D8: APX-ALT-01, APX-CORE-05 | E8: Given the intercom alert is acknowledged (ALT-02) and the pay-station alert is resolved (ALT-05). When a console acknowledges the acknowledged one, acknowledges the resolved one, and resolves the resolved one. Then each is 409 alert-transition-illegal and nothing changes — terminal states never transition (F-ALT-01 fixed). | F8: POST /v1/alerts/e7000000-0000-4000-8000-000000000701/acknowledge → 409 POST /v1/alerts/e7000000-0000-4000-8000-000000000702/acknowledge → 409 POST /v1/alerts/e7000000-0000-4000-8000-000000000702/resolve → 409 | G8: =IF(F8="",0,LEN(F8)-LEN(SUBSTITUTE(F8,CHAR(10),""))+1)
A9: ALT-08 | B9: An id that does not exist | C9: refusal | D9: APX-ALT-01 | E9: Given a console holding a stale id from a purged alert. When it reads, acknowledges, and resolves that id. Then 404 target-not-found on all three; every Alerts route declares 404 (F-ALT-02 fixed). | F9: GET /v1/alerts/e7000000-0000-4000-8000-000000000fff → 404 POST /v1/alerts/e7000000-0000-4000-8000-000000000fff/acknowledge → 404 POST /v1/alerts/e7000000-0000-4000-8000-000000000fff/resolve → 404 | G9: =IF(F9="",0,LEN(F9)-LEN(SUBSTITUTE(F9,CHAR(10),""))+1)
A10: ALT-09 | B10: An occupancy alert nobody touched expires on its own | C10: lifecycle | D10: APX-ALT-01, APX-ALT-03, APX-ALT-04 | E10: Given the occupancy engine raises occupancyThresholdExceeded when Lakeside crosses 95 percent, asking for a sixty-minute window with expiryTime. When nobody acknowledges it and occupancy falls back. Then at expiryTime the server moves it to expired, publishes apx.alert.status.v1, and a late acknowledge is 409. Every reader sees when the alert will lapse (Part 7 §7.3; F-ALT-03 fixed). | F10: POST /v1/alerts → 201 GET /v1/alerts/e7000000-0000-4000-8000-000000000704 → 200 POST /v1/alerts/e7000000-0000-4000-8000-000000000704/acknowledge → 409 | G10: =IF(F10="",0,LEN(F10)-LEN(SUBSTITUTE(F10,CHAR(10),""))+1)
A11: ALT-10 | B11: The ops board: what is open, what is serious, and the subtree rule | C11: happy | D11: APX-ALT-03 | E11: Given at 19:00 two alerts are open at Lakeside, both sourced on lanes: a major deviceFault on the exit gate (lane b2…0002) and a critical laneBlocked on the entry lane (b2…0001). When the board asks for raised alerts of major or worse at the *garage*, then at one lane, then only critical. Then the garage query returns both (a lane is inside its Place: subtree-inclusive), the lane query returns one, and the severityFloor query returns only the critical one. | F11: GET /v1/alerts → 200 GET /v1/alerts → 200 GET /v1/alerts → 200 | G11: =IF(F11="",0,LEN(F11)-LEN(SUBSTITUTE(F11,CHAR(10),""))+1)
A12: ALT-11 | B12: Wrong way at Riverside Lot: raised by the operator's own rule | C12: happy | D12: APX-ALT-03 | E12: Given a pickup enters Riverside Lot through the exit lane; the LPR system reports the read as accessEvent: entry on lane b2…0061. APX itself defines no wrong-way travel and never raises this alert (Part 13 §13.3a(6)), but wrongWayTravel stays in the registry as an operator-defined type. When the operator's own rules engine, which does care about lanes at this lot, raises wrongWayTravel with the Observation as relatedEntity, and the ops console lists today's wrong-way alerts for the lot and acknowledges the one it finds. Then the raise event carries the evidence reference, the type + place + since query finds it under the lot (the lane is in the subtree), and the acknowledge is 200. | F12: GET /v1/alerts → 200 POST /v1/alerts/e7000000-0000-4000-8000-000000000741/acknowledge → 200 | G12: =IF(F12="",0,LEN(F12)-LEN(SUBSTITUTE(F12,CHAR(10),""))+1)
A13: ALT-12 | B13: The guidance system sweeps level 2: the space-status family | C13: happy | D13: APX-ALT-03 | E13: Given the parking guidance system reconciles bay sensors against sessions every five minutes. When it finds a petrol car in the EV bay and raises iceInEvSpace with the Session as relatedEntity, and the board then lists everything raised at Lakeside since the sweep. Then 201, and a list holding the whole seeded space-status family: iceInEvSpace, occupiedWithoutCheckIn, wrongSpace, noCheckOut, overstay, each sourced on its Space, all info/warning. | F13: POST /v1/alerts → 201 GET /v1/alerts → 200 | G13: =IF(F13="",0,LEN(F13)-LEN(SUBSTITUTE(F13,CHAR(10),""))+1)
... A23: ALT-22 | B23: The shared refusals on the id-addressed Alerts routes | C23: security | D23: APX-CORE-05, APX-CORE-07, APX-ALT-01 | E23: Given a console with a transition body bug, a read-only wallboard, a tight polling loop, and an expired token. When each hits the read and transition routes. Then 400 invalid-request with errors[], 403 insufficient-scope, 429 rate-limited, and 401 unauthenticated, each declared on the route (Part 12 §12.3). | F23: POST /v1/alerts/e7000000-0000-4000-8000-000000000702/acknowledge → 400 POST /v1/alerts/e7000000-0000-4000-8000-000000000703/resolve → 400 POST /v1/alerts/e7000000-0000-4000-8000-000000000706/resolve → 403 GET /v1/alerts/e7000000-0000-4000-8000-000000000706 → 429 POST /v1/alerts/e7000000-0000-4000-8000-000000000706/acknowledge → 429 POST /v1/alerts/e7000000-0000-4000-8000-000000000706/resolve → 429 GET /v1/alerts/e7000000-0000-4000-8000-000000000706 → 401 POST /v1/alerts/e7000000-0000-4000-8000-000000000706/acknowledge → 401 POST /v1/alerts/e7000000-0000-4000-8000-000000000706/resolve → 401 | G23: =IF(F23="",0,LEN(F23)-LEN(SUBSTITUTE(F23,CHAR(10),""))+1)

Sheet apx-control
A1: ID | B1: Title | C1: Kind | D1: Annex A rows | E1: Scenario (Given / When / Then) | F1: Exchanges (request → status) | G1: Exchange count | H1: Open spec gap
A2: CTL-01 | B2: Vend the exit gate for a customer, confirmed by the sensor | C2: happy | D2: APX-CTL-01, APX-CTL-03, APX-CTL-05, APX-CTL-06 | E2: Given a driver at exit lane 2 whose ticket was resolved on the phone. When the agent vends the gate with an idempotency key, a reason, and a two-minute expiry. Then the server answers 202 with the command in accepted, and polling shows the full audit trail through succeeded with physicallyConfirmed, so the agent may say "the gate is open". | F2: POST /v1/commands → 202 GET /v1/commands/d1000000-0000-4000-8000-000000000101 → 200 | G2: =IF(F2="",0,LEN(F2)-LEN(SUBSTITUTE(F2,CHAR(10),""))+1)
A3: CTL-02 | B3: The console retries after a timeout: same key, same body | C3: edge | D3: APX-CTL-01 | E3: Given the 202 from CTL-01 never reached the console (network blip). When the console retries with the identical key and body. Then the server returns 200 with the ORIGINAL command, whatever state it has reached since; no second vend is issued. Polling an id that never existed is a 404. | F3: POST /v1/commands → 200 GET /v1/commands/d1000000-0000-4000-8000-0000000000ff → 404 | G3: =IF(F3="",0,LEN(F3)-LEN(SUBSTITUTE(F3,CHAR(10),""))+1)
A4: CTL-03 | B4: Same key reused for a different lane | C4: refusal | D4: APX-CTL-01, APX-CORE-05 | E4: Given a console bug reuses cc-7710-vend for a vend at the entry lane. When the body differs from the stored one. Then 409 idempotency-conflict; nothing is executed. | F4: POST /v1/commands → 409 | G4: =IF(F4="",0,LEN(F4)-LEN(SUBSTITUTE(F4,CHAR(10),""))+1)
A5: CTL-04 | B5: Malformed requests: no key, unknown type, throttled | C5: refusal | D5: APX-CTL-01, APX-CORE-05 | E5: Given three broken clients. When one omits Idempotency-Key, one sends a commandType that is in nobody's registry, and one exceeds the rate limit. Then each is refused with a registered problem type: the unknown type is invalid-request (Part 6 §6.1, Part 12 §12.4; F-CTL-01 fixed). | F5: POST /v1/commands → 400 POST /v1/commands → 400 POST /v1/commands → 429 | G5: =IF(F5="",0,LEN(F5)-LEN(SUBSTITUTE(F5,CHAR(10),""))+1)
A6: CTL-05 | B6: Perishable: the PARCS link is down for three minutes | C6: lifecycle | D6: APX-CTL-02, APX-CTL-03 | E6: Given the operator's link to the lane controller drops right after a vend is accepted with a 30-second expiry. When the link recovers three minutes later. Then the command has transitioned to expired, the history says why, and the gate did NOT open for whoever is in the lane now. A command submitted with an expiry already in the past is refused synchronously with 422 command-expired. | F6: POST /v1/commands → 202 GET /v1/commands/d1000000-0000-4000-8000-000000000102 → 200 POST /v1/commands → 422 | G6: =IF(F6="",0,LEN(F6)-LEN(SUBSTITUTE(F6,CHAR(10),""))+1)
A7: CTL-06 | B7: Cancel a hold-open that was issued by mistake | C7: lifecycle | D7: APX-CTL-04, APX-CTL-03 | E7: Given a supervisor issued holdGateOpen on the wrong lane. When they cancel it while it is still accepted. Then 200 with the command in cancelled, a new history entry naming who cancelled, and the gate never held. | F7: POST /v1/commands → 202 POST /v1/commands/d1000000-0000-4000-8000-000000000103/cancel → 200 | G7: =IF(F7="",0,LEN(F7)-LEN(SUBSTITUTE(F7,CHAR(10),""))+1)
A8: CTL-07 | B8: Cancel arrives after dispatch | C8: refusal | D8: APX-CTL-04 | E8: Given the vend from CTL-01 already reached the device. When a cancel is requested. Then 409 command-not-cancellable and the command's state is unchanged. Cancelling an id that does not exist has no declared response (F-CTL-06). | F8: POST /v1/commands/d1000000-0000-4000-8000-000000000101/cancel → 409 POST /v1/commands/d1000000-0000-4000-8000-0000000000ff/cancel → 404 | G8: =IF(F8="",0,LEN(F8)-LEN(SUBSTITUTE(F8,CHAR(10),""))+1)
A9: CTL-08 | B9: The device says no: rejected, and failed | C9: lifecycle | D9: APX-CTL-03, APX-CTL-05 | E9: Given the exit gate is in fault. When an agent vends it. Then the PARCS rejects the command (rejected, with the reason in the history). Later the fault clears, a second vend is dispatched, and the barrier motor times out: failed. In neither case is confirmationLevel above deviceAcknowledged, so an AI agent must tell the customer the vend was requested, not that the gate opened. | F9: POST /v1/commands → 202 GET /v1/commands/d1000000-0000-4000-8000-000000000104 → 200 POST /v1/commands → 202 GET /v1/commands/d1000000-0000-4000-8000-000000000105 → 200 | G9: =IF(F9="",0,LEN(F9)-LEN(SUBSTITUTE(F9,CHAR(10),""))+1)
A10: CTL-09 | B10: Lost ticket at the exit, fee from the deck | C10: happy | D10: APX-CTL-06, APX-CTL-08, APX-CTL-14 | E10: Given a driver at lane 2 with no ticket and no match candidates. When the agent issues lostTicket with the operator's method code. Then the command succeeds with a result naming the issued ticket, its session, and the fee (Part 6 §6.1a; F-CTL-02 fixed), and the lane inquiry shows the same ticket with amountDue equal to the deck's lostTicketFee line. | F10: GET /v1/lanes/b2000000-0000-4000-8000-000000000002/current → 200 POST /v1/commands → 202 GET /v1/commands/d1000000-0000-4000-8000-000000000106 → 200 GET /v1/lanes/b2000000-0000-4000-8000-000000000002/current → 200 | G10: =IF(F10="",0,LEN(F10)-LEN(SUBSTITUTE(F10,CHAR(10),""))+1)
A11: CTL-10 | B11: Lost ticket, but the deck has no lostTicketFee line | C11: refusal | D11: APX-CTL-08 | E11: Given the deck in force was pushed without a lostTicketFee line. When an agent issues lostTicket. Then the server refuses the POST synchronously with 422 lost-ticket-fee-undefined and creates no command: the deck is server-side state it can check before accepting (Part 6 §6.1; F-CTL-03 fixed). | F11: POST /v1/commands → 422 | G11: =IF(F11="",0,LEN(F11)-LEN(SUBSTITUTE(F11,CHAR(10),""))+1)
A12: CTL-11 | B12: Apply a cinema validation and watch the amount fall | C12: happy | D12: APX-CTL-06, APX-CTL-07 | E12: Given ticket T-1001 owes $9.00 at lane 2 and the driver saw a film. When the agent lists the place's providers, sees the cinema's benefit, and applies it. Then the lane's currentTicket.validations gains an entry with the actual amountReduced, and amountDue drops. | F12: GET /v1/validations/providers → 200 POST /v1/commands → 202 GET /v1/lanes/b2000000-0000-4000-8000-000000000002/current → 200 | G12: =IF(F12="",0,LEN(F12)-LEN(SUBSTITUTE(F12,CHAR(10),""))+1)
A13: CTL-12 | B13: A provider from the other garage | C13: refusal | D13: APX-CTL-07 | E13: Given Harbor Deck's hotel validates at Harbor Deck, not at Lakeside. When an agent applies it at Lakeside lane 2. Then 422 validation-provider-unknown; the provider list is authoritative. | F13: POST /v1/commands → 422 | G13: =IF(F13="",0,LEN(F13)-LEN(SUBSTITUTE(F13,CHAR(10),""))+1)
... A26: CTL-25 | B26: The shared refusals on every other Control route | C26: security | D26: APX-CORE-05, APX-CORE-07 | E26: Given the same four failure modes every client meets eventually. When they hit the id-addressed Control routes. Then each route answers with the shared response and a registered type: 403 for a target outside the grant or a missing scope, 429 when throttled, 401 on a dead token (Part 12 §12.3). A Lakeside token reads Harbor Deck's command, device, and lane, then tries to cancel with a read-only token: | F26: GET /v1/commands/d1000000-0000-4000-8000-000000000199 → 403 GET /v1/devices/c1000000-0000-4000-8000-000000000031 → 403 GET /v1/lanes/b2000000-0000-4000-8000-000000000003/current → 403 POST /v1/commands/d1000000-0000-4000-8000-000000000103/cancel → 403 GET /v1/commands/d1000000-0000-4000-8000-000000000101 → 429 POST /v1/commands/d1000000-0000-4000-8000-000000000103/cancel → 429 GET /v1/devices/c1000000-0000-4000-8000-000000000003 → 429 GET /v1/lanes/b2000000-0000-4000-8000-000000000002/current → 429 GET /v1/commands/d1000000-0000-4000-8000-000000000101 → 401 POST /v1/commands/d1000000-0000-4000-8000-000000000103/cancel → 401 GET /v1/devices/c1000000-0000-4000-8000-000000000003 → 401 GET /v1/lanes/b2000000-0000-4000-8000-000000000002/current → 401 | G26: =IF(F26="",0,LEN(F26)-LEN(SUBSTITUTE(F26,CHAR(10),""))+1)

Sheet apx-credentials
A1: ID | B1: Title | C1: Kind | D1: Annex A rows | E1: Scenario (Given / When / Then) | F1: Exchanges (request → status) | G1: Exchange count | H1: Open spec gap
A2: CRD-01 | B2: Issue a keycard for a new monthly parker | C2: happy | D2: APX-CRD-01, APX-CRD-05, APX-CRD-06 | E2: Given Maya Okafor signs a monthly contract starting January 1 and the front desk pulls an HID proximity card from stock. When the desk issues it with an idempotency key, a $25 deposit, and the validity window. Then the server answers 201 with the record in issued (nothing opens the gate yet), publishes apx.credentials.status.v1, and a read returns the same record with its identification — visible only because the token carries apx.credentials:*. | F2: POST /v1/credentials → 201 GET /v1/credentials/d6000000-0000-4000-8000-000000000101 → 200 | G2: =IF(F2="",0,LEN(F2)-LEN(SUBSTITUTE(F2,CHAR(10),""))+1)
A3: CRD-02 | B3: The desk console retries: same key, then the wrong key | C3: edge | D3: APX-CRD-01, APX-CORE-05 | E3: Given the 201 from CRD-01 was lost to a Wi-Fi drop at the front desk. When the console retries with the identical key and body, then a console bug reuses the key for a different card, then a third client forgets the header altogether. Then 200 with the ORIGINAL record (one card issued, not two), 409 idempotency-conflict, and 400 idempotency-key-required. | F3: POST /v1/credentials → 200 POST /v1/credentials → 409 POST /v1/credentials → 400 | G3: =IF(F3="",0,LEN(F3)-LEN(SUBSTITUTE(F3,CHAR(10),""))+1)
A4: CRD-03 | B4: Malformed record, unknown holder | C4: refusal | D4: APX-CRD-01, APX-CORE-05 | E4: Given two broken issue requests. When one omits credentialType and one names a RightHolder that does not exist. Then 400 invalid-request and 422 reference-unknown, both declared on the operation and both now registered in Part 12 and named in its descriptions (F-CRD-02 and F-CRD-01, fixed). | F4: POST /v1/credentials → 400 POST /v1/credentials → 422 | G4: =IF(F4="",0,LEN(F4)-LEN(SUBSTITUTE(F4,CHAR(10),""))+1)
A5: CRD-04 | B5: Ray's fob: issued at the desk, activated on collection, seen by a stock APDS lane | C5: lifecycle | D5: APX-CRD-01, APX-CRD-02, APX-CORE-02 | E5: Given Ray Delgado's monthly right starts today and the desk has a garage-remote fob ready. When the desk issues it at 09:00 and activates it at 09:05 when Ray collects it. Then the record goes issued → active, and the entry lane — an APDS-native client that only reads /rights/assigned — sees a CredentialAssigned whose identifier points at the CredentialRecord, without ever speaking APX. | F5: POST /v1/credentials → 201 POST /v1/credentials/d6000000-0000-4000-8000-000000000103/activate → 200 GET /rights/assigned → 200 | G5: =IF(F5="",0,LEN(F5)-LEN(SUBSTITUTE(F5,CHAR(10),""))+1)
A6: CRD-05 | B6: Activate twice, activate nothing | C6: refusal | D6: APX-CRD-01 | E6: Given the fob from CRD-04 is already active. When the desk double-clicks Activate, then a stale bookmark hits an id that never existed, on both the read and the activate route. Then 409 credential-transition-illegal (active is not issued), and 404 twice. | F6: POST /v1/credentials/d6000000-0000-4000-8000-000000000103/activate → 409 GET /v1/credentials/d6000000-0000-4000-8000-0000000000ff → 404 POST /v1/credentials/d6000000-0000-4000-8000-0000000000ff/activate → 404 | G6: =IF(F6="",0,LEN(F6)-LEN(SUBSTITUTE(F6,CHAR(10),""))+1)
A7: CRD-06 | B7: Suspended for non-payment until the 17th, denied at the gate, resumed by the clock | C7: lifecycle | D7: APX-CRD-01, APX-CRD-02, APX-CRD-04, APX-CRD-06 | E7: Given Ray's September invoice is unpaid on the 10th. When billing suspends the fob with until set to the 17th, Ray presents it at the entry lane that evening, and the 17th arrives. Then the record shows suspension, the stock APDS query on the AssignedRight comes back empty, the lane denies with credentialSuspended and the access event is published, and at the appointed instant the server resumes it with actor system and publishes the status event. | F7: POST /v1/credentials/d6000000-0000-4000-8000-000000000103/suspend → 200 GET /rights/assigned → 200 | G7: =IF(F7="",0,LEN(F7)-LEN(SUBSTITUTE(F7,CHAR(10),""))+1)
A8: CRD-07 | B8: Suspend and resume by hand, and the transitions that do not exist | C8: lifecycle | D8: APX-CRD-01, APX-CRD-02 | E8: Given Ray is travelling for a week and asks the desk to freeze the fob without an end date. When the desk suspends it on the 18th and resumes it on the 22nd, then clicks Resume again, and then tries to suspend a hangtag that was issued but never collected. Then 200, 200, 409 credential-transition-illegal (already active), and 409 credential-transition-illegal (issued cannot be suspended, only activated or revoked); an unknown id is 404 on both routes. | F8: POST /v1/credentials/d6000000-0000-4000-8000-000000000103/suspend → 200 POST /v1/credentials/d6000000-0000-4000-8000-000000000103/resume → 200 POST /v1/credentials/d6000000-0000-4000-8000-000000000103/resume → 409 POST /v1/credentials/d6000000-0000-4000-8000-000000000110/suspend → 409 POST /v1/credentials/d6000000-0000-4000-8000-0000000000ff/suspend → 404 POST /v1/credentials/d6000000-0000-4000-8000-0000000000ff/resume → 404 | G8: =IF(F8="",0,LEN(F8)-LEN(SUBSTITUTE(F8,CHAR(10),""))+1)
A9: CRD-08 | B9: Reported lost from active, stolen while suspended, and the states that cannot be lost | C9: lifecycle | D9: APX-CRD-01, APX-CRD-02 | E9: Given Maya calls at noon on the 19th: the keycard is gone (scenario 20). When the agent reports it lost; later, Northshore Plumbing's windshield transponder — suspended for an account balance — is reported stolen from a van; then someone tries report-lost on the uncollected hangtag and again on Maya's already-lost card. Then 200 (active → lost), 200 (suspended → lost), 409, 409, and 404 for an unknown id. From each lost instant the lane denies the credential. | F9: POST /v1/credentials/d6000000-0000-4000-8000-000000000101/report-lost → 200 POST /v1/credentials/d6000000-0000-4000-8000-000000000104/report-lost → 200 POST /v1/credentials/d6000000-0000-4000-8000-000000000110/report-lost → 409 POST /v1/credentials/d6000000-0000-4000-8000-000000000101/report-lost → 409 POST /v1/credentials/d6000000-0000-4000-8000-0000000000ff/report-lost → 404 | G9: =IF(F9="",0,LEN(F9)-LEN(SUBSTITUTE(F9,CHAR(10),""))+1)
A10: CRD-09 | B10: Replace the lost card from pre-encoded stock, in one call | C10: happy | D10: APX-CRD-01, APX-CRD-03, APX-CRD-06 | E10: Given Maya's card is lost and the front desk holds pre-encoded stock. When the agent replaces it, forfeiting the old deposit against the new one, and the console retries the same call after a timeout. Then 201 with the successor already active, inheriting holder, account, assigned right, places, and validity; the predecessor reads replaced with replacedBy and its deposit forfeited; the retry returns 200 with the SAME successor. The AssignedRight swapped cards in one AssignedRightUpdated. | F10: POST /v1/credentials/d6000000-0000-4000-8000-000000000101/replace → 201 GET /v1/credentials/d6000000-0000-4000-8000-000000000101 → 200 POST /v1/credentials/d6000000-0000-4000-8000-000000000101/replace → 200 | G10: =IF(F10="",0,LEN(F10)-LEN(SUBSTITUTE(F10,CHAR(10),""))+1)
A11: CRD-10 | B11: Everything replace refuses | C11: refusal | D11: APX-CRD-01, APX-CRD-03, APX-CORE-05 | E11: Given the replaced card from CRD-09, the hangtag revoked in CRD-12, the seasonal hangtag that expired in CRD-13, and the uncollected hangtag still in issued. When a replacement is requested on each, then on Ray's fob with a successor identification that is already live, then with the key from CRD-09 and a different body, then without a key, then on an id that does not exist. Then 409 credential-not-replaceable three times, 409 credential-transition-illegal for issued (F-CRD-04, fixed: §21.1 rule 1 now says so, and credential-not-replaceable is reserved for terminal states), 409 credential-identification-in-use, 409 idempotency-conflict, 400 idempotency-key-required, and 404. | F11: POST /v1/credentials/d6000000-0000-4000-8000-000000000101/replace → 409 POST /v1/credentials/d6000000-0000-4000-8000-000000000110/replace → 409 POST /v1/credentials/d6000000-0000-4000-8000-000000000112/replace → 409 POST /v1/credentials/d6000000-0000-4000-8000-000000000113/replace → 409 POST /v1/credentials/d6000000-0000-4000-8000-000000000103/replace → 409 POST /v1/credentials/d6000000-0000-4000-8000-000000000101/replace → 409 POST /v1/credentials/d6000000-0000-4000-8000-000000000103/replace → 400 POST /v1/credentials/d6000000-0000-4000-8000-0000000000ff/replace → 404 | G11: =IF(F11="",0,LEN(F11)-LEN(SUBSTITUTE(F11,CHAR(10),""))+1)
A12: CRD-11 | B12: 6 PM: the old card at the gate, and the next morning's question | C12: happy | D12: APX-CRD-02, APX-CRD-04, APX-CRD-05 | E12: Given the old card was taken off the AssignedRight at noon. When someone presents it at the entry lane at 18:02 and Maya asks the next morning whether anyone used it. Then the APDS-native lane finds no right carrying C-0048812 and denies; the server records the attempt with denialReason: credentialReplaced and publishes it; the history route returns newest-first, filters by outcome, pages, and 404s for an unknown credential. | F12: GET /v1/credentials/d6000000-0000-4000-8000-000000000101/access-events → 200 GET /v1/credentials/d6000000-0000-4000-8000-000000000101/access-events → 200 GET /v1/credentials/d6000000-0000-4000-8000-000000000101/access-events → 200 GET /v1/credentials/d6000000-0000-4000-8000-0000000000ff/access-events → 404 | G12: =IF(F12="",0,LEN(F12)-LEN(SUBSTITUTE(F12,CHAR(10),""))+1)
A13: CRD-12 | B13: Revoke: never collected, stolen, and twice is once too many | C13: lifecycle | D13: APX-CRD-01, APX-CRD-02, APX-CRD-06 | E13: Given a contractor hangtag issued on the 1st that nobody ever collected, and Northshore's transponder now lost with a police reference. When the desk revokes the hangtag from issued and the fleet desk revokes the transponder from lost, then a second revoke lands on each, and one on Maya's replaced card. Then 200, 200, and 409 credential-transition-illegal three times: revoked and replaced are terminal. The transponder's CredentialAssigned is gone from the fleet AssignedRight; an unknown id is 404. | F13: POST /v1/credentials/d6000000-0000-4000-8000-000000000110/revoke → 200 POST /v1/credentials/d6000000-0000-4000-8000-000000000104/revoke → 200 GET /rights/assigned → 200 POST /v1/credentials/d6000000-0000-4000-8000-000000000110/revoke → 409 POST /v1/credentials/d6000000-0000-4000-8000-000000000101/revoke → 409 POST /v1/credentials/d6000000-0000-4000-8000-0000000000ff/revoke → 404 | G13: =IF(F13="",0,LEN(F13)-LEN(SUBSTITUTE(F13,CHAR(10),""))+1)
... A26: CRD-25 | B26: Windows already over, and a card that activates itself | C26: edge | D26: APX-CRD-01, APX-CRD-06 | E26: Given a bulk import that still carries last season's contract, a billing batch that queues suspensions and replays them late, and a contractor hangtag the desk wants live the moment its window opens. When the import issues a card whose validity.end has passed, the batch suspends Maya's card until a time already gone, and the desk issues the hangtag with activateOnStart: true and a validity.start already past. Then 422 request-unprocessable twice, nothing written (F-CRD-11, fixed: §21.1 rule 7) — and 201 with the hangtag already active, activated by system at issue (F-CRD-06, fixed: §21.1 rule 6), materialized per §21.2 and published like any other transition. | F26: POST /v1/credentials → 422 POST /v1/credentials/d6000000-0000-4000-8000-000000000102/suspend → 422 POST /v1/credentials → 201 | G26: =IF(F26="",0,LEN(F26)-LEN(SUBSTITUTE(F26,CHAR(10),""))+1)

Sheet apx-data
A1: ID | B1: Title | C1: Kind | D1: Annex A rows | E1: Scenario (Given / When / Then) | F1: Exchanges (request → status) | G1: Exchange count | H1: Open spec gap
A2: DATA-01 | B2: A plain APDS client pulls the hierarchy, no APX anywhere | C2: happy | D2: APX-DATA-01, APX-DATA-07, APX-CORE-01, APX-CORE-02 | E2: Given the city platform's first integration is a stock APDS 4.1 client that has never heard of APX. When it lists places, reads the garage, and reads the garage at an older version. Then it observes pure APDS 4.1: a HierarchyElementList, a Place whose hierarchyElementReference carries the native Supply and DemandTable, and version 6 of the same element. No APX header, no APX parameter, no APX field in the response. | F2: GET /places → 200 GET /places/b1000000-0000-4000-8000-000000000001 → 200 GET /places/b1000000-0000-4000-8000-000000000001 → 200 | G2: =IF(F2="",0,LEN(F2)-LEN(SUBSTITUTE(F2,CHAR(10),""))+1)
A3: DATA-02 | B3: First sync with the coarse fallback: modified_since and tombstones | C3: happy | D3: APX-DATA-05, APX-DATA-07, APX-CORE-02 | E3: Given the city platform holds no cursor yet. When it pulls sessions changed since 17 September with the native modified_since (Part 5 §5.2 rule 3). Then a stock SessionList whose deletedReferences names the session purged on the 20th — APDS's own tombstone shape, before any APX parameter is used. | F3: GET /sessions → 200 | G3: =IF(F3="",0,LEN(F3)-LEN(SUBSTITUTE(F3,CHAR(10),""))+1)
A4: DATA-03 | B4: Switch to the cursor feed and drain it | C4: happy | D4: APX-DATA-03, APX-DATA-04, APX-DATA-01 | E4: Given the platform has finished its full pull and been handed cursor c:00041. When it asks /sessions for changes after that cursor. Then a ChangeFeedPage: change-mode items carrying identity plus only the changed fields, a tombstone, a new cursor, and next pointing at the immediately available second page; the second page ends with next: null, so the platform polls later with c:00043. | F4: GET /sessions → 200 GET /sessions → 200 | G4: =IF(F4="",0,LEN(F4)-LEN(SUBSTITUTE(F4,CHAR(10),""))+1)
A5: DATA-04 | B5: Mirroring the rate deck, with the negotiable flag riding inside | C5: happy | D5: APX-DATA-03, APX-DATA-01, APX-CORE-04 | E5: Given the operator's call platform needs the deck. When it pulls /rates for the garage in mode=full once, then in mode=change with the cursor. Then the full list carries the standard deck and the flat $20 table with its apds-ext:apx:ratepolicy@1.0 decoration, and the change page carries only the corrected line on v8. The full-mode RateTable validates once the data overlay drops the two phantom required members (erratum 004), and the decoration lives in the extensions member the overlay declares on every APDS entity (erratum 010). | F5: GET /rates → 200 GET /rates → 200 | G5: =IF(F5="",0,LEN(F5)-LEN(SUBSTITUTE(F5,CHAR(10),""))+1)
A6: DATA-05 | B6: The other two feed routes: places and assigned rights | C6: happy | D6: APX-DATA-03, APX-DATA-04 | E6: Given the owner's BI platform holds cursors for /places and /rights/assigned. When it polls both in mode=change. Then the places page carries one item — the garage with only its demand table changed — and the assigned-rights page carries the monthly holder's renewed expiry plus a tombstone for a cancelled permit. Each feed is its own class, its own cursor, its own ordering. | F6: GET /places → 200 GET /rights/assigned → 200 | G6: =IF(F6="",0,LEN(F6)-LEN(SUBSTITUTE(F6,CHAR(10),""))+1)
A7: DATA-06 | B7: The warehouse crashed mid-load: replay from the old cursor | C7: lifecycle | D7: APX-DATA-04 | E7: Given the BI loader wrote cursor c:00042 to disk only after committing the page — and died between the two. When it restarts and replays from the cursor it last persisted, c:00041. Then the server returns exactly the page it returned in DATA-03: same item, same tombstone, same next cursor. Replaying an issued cursor yields every change after it exactly once; the loader's idempotent upsert makes the duplicate harmless. | F7: GET /sessions → 200 | G7: =IF(F7="",0,LEN(F7)-LEN(SUBSTITUTE(F7,CHAR(10),""))+1)
A8: DATA-07 | B8: Back from a two-week outage: the cursor is too old | C8: refusal | D8: APX-DATA-05, APX-DATA-03 | E8: Given the city platform was down from 8 to 24 September and still holds cursor c:00007, issued on the 8th. When it presents it. Then 404 target-not-found — the server retains seven days, the cursor is sixteen days old — and the platform re-syncs with mode=full before taking a fresh cursor. The cursor is an APX parameter, so the 404 the data overlay declares on the feed routes is always a Problem (Part 5 §5.2). | F8: GET /sessions → 404 GET /sessions → 200 | G8: =IF(F8="",0,LEN(F8)-LEN(SUBSTITUTE(F8,CHAR(10),""))+1)
A9: DATA-08 | B9: A cursor from another filter set, and from another credential | C9: refusal | D9: APX-DATA-04, APX-DATA-05 | E9: Given cursor c:00043 was issued to city-platform for the unfiltered sessions feed. When the same credential presents it with a place filter added, and then owner-bi presents it verbatim. Then both are 404 target-not-found: a cursor is scoped to (class, credential, filter set) and never composes across them (§5.2 rule 5). Same 404 as DATA-07. | F9: GET /sessions → 404 GET /sessions → 404 | G9: =IF(F9="",0,LEN(F9)-LEN(SUBSTITUTE(F9,CHAR(10),""))+1)
A10: DATA-09 | B10: The city's grant grows: Marina Lot arrives as a grantAddition | C10: edge | D10: APX-DATA-06, APX-DATA-03, APX-DATA-04 | E10: Given the operator adds Marina Lot to the city platform's apx_places grant overnight. When the platform polls /places with its existing cursor. Then the first page after the change carries grantAdditions naming the new subtree root — the cursor does not retroactively cover its history — and the platform runs a mode=full pull for that subtree before trusting the feed for it. The next page has no grantAdditions. The subtree pull uses the native place filter the data overlay adds to /places (subtree-inclusive, as on /sessions). | F10: GET /places → 200 GET /places → 200 GET /places → 200 | G10: =IF(F10="",0,LEN(F10)-LEN(SUBSTITUTE(F10,CHAR(10),""))+1)
A11: DATA-10 | B11: The PARCS pushes a new session in full mode | C11: happy | D11: APX-DATA-01, APX-DATA-02, APX-CORE-03 | E11: Given a car takes ticket T-1101 at the entry lane. When lakeside-parcs posts the session with a client-supplied id and no APX-Update-Mode header (so full, stock APDS behaviour). Then 201 with APDS's ResponseStatus, and a read shows the server-assigned initiator. The header is declared on the native PUTs only; a create always carries full state (Part 5 §5.1). | F11: POST /sessions → 201 GET /sessions/c4000000-0000-4000-8000-000000000101 → 200 | G11: =IF(F11="",0,LEN(F11)-LEN(SUBSTITUTE(F11,CHAR(10),""))+1)
A12: DATA-11 | B12: The PARCS retries the same POST, and posts a broken one | C12: refusal | D12: APX-CORE-03, APX-DATA-01 | E12: Given the PARCS never saw the 201 from DATA-10 and retries. When it re-posts the same client-supplied id, and separately posts a session with no actualStart. Then 409 with the conflicting id listed in ids (APDS convention; APX-CORE-03), and 400. Both keep the APDS ResponseStatus shape; with Accept: application/problem+json the same 409 is the registered id-collision problem (Part 5 §5.1a). | F12: POST /sessions → 409 POST /sessions → 400 | G12: =IF(F12="",0,LEN(F12)-LEN(SUBSTITUTE(F12,CHAR(10),""))+1)
A13: DATA-12 | B13: Close the session with a change-mode PUT: absent means unchanged | C13: happy | D13: APX-DATA-02, APX-DATA-01 | E13: Given T-1101 exits at 21:40. When the PARCS sends APX-Update-Mode: change with identity, actualEnd, and the closed segment — nothing else. Then 200, and a read shows version 2 with the credentials and vehicle exactly as before: absent meant unchanged. The change-mode body validates as a ChangePayload (Part 5 §5.1a), not as the full native Session. | F13: PUT /sessions/c4000000-0000-4000-8000-000000000101 → 200 GET /sessions/c4000000-0000-4000-8000-000000000101 → 200 | G13: =IF(F13="",0,LEN(F13)-LEN(SUBSTITUTE(F13,CHAR(10),""))+1)
... A34: DATA-33 | B34: Stale cursors on every feed, and the refusals APDS forgot to declare | C34: refusal | D34: APX-DATA-05, APX-DATA-03, APX-DATA-01 | E34: Given the BI platform's cursors for places, rates, assigned rights, and observations all predate the 7-day window, and a PARCS that sends a broken observation, a duplicate observation, a broken rate table, a duplicate rate table, and an update to an assigned right that does not exist. Then 404 target-not-found on each feed (Part 5 §5.2 rule 2), and the APDS ResponseStatus 400/409/404 that the data overlay now declares on POST /observations, POST /rates, and PUT /rights/assigned/{id} (APX errata 005 and 012). | F34: GET /places → 404 GET /rates → 404 GET /rights/assigned → 404 GET /observations → 404 POST /observations → 400 POST /observations → 409 POST /rates → 400 POST /rates → 409 PUT /rights/assigned/e2000000-0000-4000-8000-0000000000fe → 404 | G34: =IF(F34="",0,LEN(F34)-LEN(SUBSTITUTE(F34,CHAR(10),""))+1)

Sheet apx-discovery
A1: ID | B1: Title | C1: Kind | D1: Annex A rows | E1: Scenario (Given / When / Then) | F1: Exchanges (request → status) | G1: Exchange count | H1: Open spec gap
A2: DSC-01 | B2: A client with nothing but a hostname | C2: happy | D2: APX-CORE-09, APX-CORE-06, APX-CORE-12 | E2: Given a new integrator who has been told only "api.lakeside-garage.example". When they fetch /.well-known/apx-configuration at the host root with no credentials. Then they get the token endpoint, the APDS version, the claimed classes, and the registry locations, and can start the OAuth2 client-credentials flow. Harbor Deck's own PARCS starter host answers the same request with the three-class minimum. Lakeside's document also says which edition and which registry versions it validates against, and which optional features it offers (Part 16 §16.1; F-DSC-05 and F-DSC-01 fixed — the members land in ApxConfiguration when the integrator points the component at the discovery domain schema). | F2: GET /.well-known/apx-configuration → 200 GET /.well-known/apx-configuration → 200 | G2: =IF(F2="",0,LEN(F2)-LEN(SUBSTITUTE(F2,CHAR(10),""))+1)
A3: DSC-02 | B3: The console bootstraps: token, then its own capability document | C3: happy | D3: APX-DSC-01, APX-DSC-02, APX-DSC-04, APX-CORE-06 | E3: Given the console has exchanged its client credentials at the token endpoint from DSC-01 and holds a JWT with apx_org a1…0001 and apx_places ["b1…0001"]. When it calls GET /v1/discovery. Then the document names the client, reflects the scopes, org, and places exactly, lists the classes the token can use (the host's eight minus apx-alerts and apx-lpr, which no scope reaches), the concrete endpoints, all fifteen command types including the two optional-feature commands the host supports, the topics it may subscribe to, and advisory limits. The response is private and cacheable for five minutes. | F3: GET /v1/discovery → 200 | G3: =IF(F3="",0,LEN(F3)-LEN(SUBSTITUTE(F3,CHAR(10),""))+1)
A4: DSC-03 | B4: Two clients, two documents | C4: happy | D4: APX-DSC-03, APX-DSC-01 | E4: Given CityPark Analytics holds a read-only token on both garages. When it calls the same GET /v1/discovery on the same host, a minute after the console did. Then its document differs in every credential-derived member: another client id and organisation, two place roots, only the data and event classes, no control endpoints, an explicitly empty commandTypes, and only the topics a data reader may take. | F4: GET /v1/discovery → 200 | G4: =IF(F4="",0,LEN(F4)-LEN(SUBSTITUTE(F4,CHAR(10),""))+1)
A5: DSC-04 | B5: The document is a promise, not advertising | C5: security | D5: APX-DSC-02, APX-CORE-07 | E5: Given the console's document from DSC-02 lists no /v1/alerts and no /v1/lpr/reads. When a console developer "just tries" both, and then uses a listed endpoint (POST /v1/commands) against Harbor Deck's exit lane. Then the two unlisted endpoints fail 403 insufficient-scope, and the listed one fails 403 insufficient-grant: soundness covers the endpoint, the grant still bounds the inputs. | F5: GET /v1/alerts → 403 GET /v1/lpr/reads → 403 POST /v1/commands → 403 | G5: =IF(F5="",0,LEN(F5)-LEN(SUBSTITUTE(F5,CHAR(10),""))+1)
A6: DSC-05 | B6: An endpoint of a class the host does not claim | C6: refusal | D6: APX-DSC-02 | E6: Given the host claims no apx-valet. When a valet-app developer who has the console credential calls the valet queue for Lakeside. Then 404 target-not-found: an endpoint of a class the server does not claim is not there, while an endpoint it implements but the token's scopes do not cover is 403 insufficient-scope (DSC-04). Part 9 §9.3a settles it and Part 16 §16.2 and APX-DSC-02 now say the same (F-DSC-02 fixed; no new problem type needed). | F6: GET /v1/valet/queue → 404 | G6: =IF(F6="",0,LEN(F6)-LEN(SUBSTITUTE(F6,CHAR(10),""))+1)
A7: DSC-06 | B7: The explicit wildcard, and the token with no places at all | C7: security | D7: APX-CORE-08, APX-DSC-01 | E7: Given two tokens minted the same morning: Lakeside's operations client with the deliberate apx_places: ["*"], and a trial IVR client whose registration forgot the claim entirely. When each calls discovery. Then the first document carries the single wildcard entry and every data and alert endpoint; the second reflects no places and, fail-closed, lists only what can succeed without one. A missing claim is reflected as places: [], never an absent member, and "callable" means callable for at least one target inside the granted places, so the place-targeting routes are left out (Part 16 §16.2; F-DSC-09 fixed). | F7: GET /v1/discovery → 200 GET /v1/discovery → 200 | G7: =IF(F7="",0,LEN(F7)-LEN(SUBSTITUTE(F7,CHAR(10),""))+1)
A8: DSC-07 | B8: Discovery without a usable token | C8: refusal | D8: APX-CORE-06 | E8: Given a script that calls /v1/discovery before it has fetched a token, and a dashboard whose token expired overnight. When each calls. Then 401 unauthenticated both times (Part 12; F-DSC-03 fixed). | F8: GET /v1/discovery → 401 GET /v1/discovery → 401 | G8: =IF(F8="",0,LEN(F8)-LEN(SUBSTITUTE(F8,CHAR(10),""))+1)
A9: DSC-08 | B9: A token with no APX scope, and a client that polls discovery in a loop | C9: refusal | D9: APX-DSC-01, APX-CORE-07 | E9: Given a legacy APDS client whose token carries only the APDS po scope, and a misbehaving SDK that calls discovery before every request. When the first calls /v1/discovery ("any APX scope", §16.2) and the second exceeds its advisory limit. Then 403 insufficient-scope and 429 rate-limited, both declared on the operation (F-DSC-10 fixed). | F9: GET /v1/discovery → 403 GET /v1/discovery → 429 | G9: =IF(F9="",0,LEN(F9)-LEN(SUBSTITUTE(F9,CHAR(10),""))+1)
A10: DSC-09 | B10: A class claimed without its dependency | C10: edge | D10: APX-CORE-09 | E10: Given Harbor Deck's PARCS vendor turns on the resolution module before the command plane, and later a payment-history module without accounts. When the bootstrap document advertises apx-resolution without apx-control, then apx-payment-history without apx-accounts. Then both documents validate against the schema, and both are non-conforming: Part 16 §16.1 requires the claim to be closed under Part 3 §3.1's dependency table, and a client reading either treats apx-resolution and then apx-payment-history as not offered (F-DSC-08 fixed in prose; the Annex A row and a tools check are with the integrator). | F10: GET /.well-known/apx-configuration → 200 GET /.well-known/apx-configuration → 200 | G10: =IF(F10="",0,LEN(F10)-LEN(SUBSTITUTE(F10,CHAR(10),""))+1)
A11: DSC-10 | B11: The grant is narrowed; the document follows, after the cache | C11: edge | D11: APX-DSC-01, APX-DSC-03 | E11: Given Lakeside's administrator narrows the console's grant from the whole garage to its exit level while the console still holds a document fetched at 08:03. When the console re-fetches at 08:09, after the five-minute max-age, with a token re-issued under the new grant. Then places names only the exit level and everything else is unchanged. Between 08:04 and 08:08 the old document said the entry level was reachable and the server said otherwise. Part 16 §16.2 now closes that window: a grant change takes effect through a new token, the document is valid for its token's lifetime, max-age is capped by that lifetime, and a client that meets a 403 on a listed endpoint refetches discovery before retrying (F-DSC-14 fixed). | F11: GET /v1/discovery → 200 | G11: =IF(F11="",0,LEN(F11)-LEN(SUBSTITUTE(F11,CHAR(10),""))+1)
A12: DSC-11 | B12: A vendor extension shows up in both documents | C12: edge | D12: APX-DSC-02, APX-CORE-04 | E12: Given AcmeCorp has added a loyalty domain to the Lakeside host per Part 3 §3.3: endpoints under /apx/x/acmecorp/, topics under acmecorp., and its own conformance class. When the bootstrap and discovery documents are fetched by a client whose token carries the vendor scope. Then both documents carry the vendor entries: vendor endpoints and topics appear under the same soundness rule as APX ones, the vendor class is acmecorp-loyalty (<vendor-ns>-<class>, never apx-), and a client that does not know it ignores it (Part 3 §3.1, Part 16 §16.2; F-DSC-04 fixed). The decoration sits in the discovery document's declared extensions container (F-DSC-06 fixed; the bootstrap document gets the same container with the integrator's component change). | F12: GET /.well-known/apx-configuration → 200 GET /v1/discovery → 200 | G12: =IF(F12="",0,LEN(F12)-LEN(SUBSTITUTE(F12,CHAR(10),""))+1)
A13: DSC-12 | B13: Lakeside joins the CityPark aggregator | C13: lifecycle | D13: APX-CORE-09, APX-DSC-01, APX-DSC-03 | E13: Given Lakeside Garage is migrated into CityPark's aggregating implementation (Part 18 §18.3), which mounts its API under /parking/v1 on a shared city host. When the console re-runs onboarding at the new host: bootstrap at the host root, a new registration at CityPark's IdP with apx_places naming exactly the migrated subtree root, then discovery. Then the bootstrap document shows a different class set (no resolution, no LPR) and a different token endpoint, and the discovery document proves the boundary before any traffic flows. The bootstrap document's apiBase says where the bundle's paths are mounted, so the console needs nothing out of band, and discovery path values are relative to it (Part 16 §16.1; F-DSC-13 fixed, pending the integrator's component change). | F13: GET /.well-known/apx-configuration → 200 GET /v1/discovery → 200 | G13: =IF(F13="",0,LEN(F13)-LEN(SUBSTITUTE(F13,CHAR(10),""))+1)
... A17: DSC-16 | B17: A read-only control dashboard can see the optional features | C17: happy | D17: APX-DSC-04, APX-DSC-01 | E17: Given Lakeside's wall dashboard holds only apx.control:read. When it calls discovery. Then commandTypes is empty, since it may execute nothing, and features still lists negotiatedRates and ticketMatching, so it knows to render the negotiated-rate and matched-ticket panels of the lane inquiry (Part 6 §6.5, Part 16 §16.2; F-DSC-01 fixed). | F17: GET /v1/discovery → 200 GET /.well-known/apx-configuration → 429 | G17: =IF(F17="",0,LEN(F17)-LEN(SUBSTITUTE(F17,CHAR(10),""))+1)

Sheet apx-events
A1: ID | B1: Title | C1: Kind | D1: Annex A rows | E1: Scenario (Given / When / Then) | F1: Exchanges (request → status) | G1: Exchange count | H1: Open spec gap
A2: EVT-01 | B2: A stock APDS 4.1 client subscribes and sees pure APDS | C2: happy | D2: APX-EVT-01, APX-CORE-02 | E2: Given the city's legacy curb integration, written against APDS 4.1 alone, posts a stock EventSubscription with no Prefer header. When Lakeside's policy routes new subscriptions to back-office approval. Then the answer is APDS's own 202 ResponseStatus, with the new subscription's id as the single entry of ids[] (Part 8 §8.1 makes that a MUST, so a stock client can revoke what it created). A second stock client at a server that auto-activates gets the stock 200. | F2: POST /webhooks → 202 POST /webhooks → 200 | G2: =IF(F2="",0,LEN(F2)-LEN(SUBSTITUTE(F2,CHAR(10),""))+1)
A3: EVT-02 | B3: An APX client asks for the representation and gets the secret once | C3: happy | D3: APX-EVT-01, APX-EVT-07, APX-EVT-06 | E3: Given the city platform's APX-aware integration. When it subscribes with Prefer: return=representation, mixing an APDS topic with two APX topics and filtering to Lakeside, alerts at warning and above. Then 201 with the full subscription and a server-generated secret of at least 32 bytes, disclosed in this response only; the list afterwards shows the same subscription without it. | F3: POST /webhooks → 201 GET /webhooks → 200 | G3: =IF(F3="",0,LEN(F3)-LEN(SUBSTITUTE(F3,CHAR(10),""))+1)
A4: EVT-03 | B4: Refused at creation: unknown topic, no endpoint, empty topics | C4: refusal | D4: APX-EVT-01, APX-CORE-05 | E4: Given three broken clients. When one asks for a topic version that does not exist, one asks for webhook transport without an endpoint, and one sends an empty topic list. Then each is a 400: unknown-topic for the first, invalid-request with an errors[] pointer for the other two. | F4: POST /webhooks → 400 POST /webhooks → 400 POST /webhooks → 400 | G4: =IF(F4="",0,LEN(F4)-LEN(SUBSTITUTE(F4,CHAR(10),""))+1)
A5: EVT-04 | B5: The first delivery: a stock APDS topic, signed the APX way | C5: happy | D5: APX-EVT-02, APX-EVT-04, APX-EVT-06 | E5: Given subscription e8…0003 is active. When a car takes a ticket at the entry lane and a Session is created. Then the city endpoint receives one POST carrying the envelope, signed with the secret from EVT-02: APX-Signature over APX-Timestamp + "." + body, a fresh APX-Delivery-Id, no APX-Key-Id (no rotation in progress). data is the stock APDS Session, because the topic is an APDS EventTypeEnum value; subject references it. | F5: GET /webhooks/e8000000-0000-4000-8000-000000000003/deliveries → 200 | G5: =IF(F5="",0,LEN(F5)-LEN(SUBSTITUTE(F5,CHAR(10),""))+1)
A6: EVT-05 | B6: The endpoint is down: one event id, five delivery ids, the schedule | C6: lifecycle | D6: APX-EVT-03, APX-EVT-04 | E6: Given the city platform deploys at 02:00 and its endpoint returns 503 for the next hour and a half. When a device-state event is published at 02:00:00. Then Lakeside retries on the normative schedule — 0s, 30s, 2m, 10m, 1h, then hourly — with the same envelope id every time and a new APX-Delivery-Id per attempt. The schedule values are delays between consecutive attempts (Part 8 §8.3), and the ledger's attemptHistory shows every attempt's delivery id, time, and code; the operator filters the ledger to the one event it is chasing. | F6: GET /webhooks/e8000000-0000-4000-8000-000000000003/deliveries → 200 GET /webhooks/e8000000-0000-4000-8000-000000000003/deliveries → 200 | G6: =IF(F6="",0,LEN(F6)-LEN(SUBSTITUTE(F6,CHAR(10),""))+1)
A7: EVT-06 | B7: Twenty-four hours later: failed, the self-referential event, the alert | C7: lifecycle | D7: APX-EVT-03, APX-EVT-06 | E7: Given the city endpoint stays down for a full day. When the last hourly retry (attempt 27, at 01:12:30 on the 26th — the last one that falls within 24 hours of the first) also fails. Then the subscription transitions to failed, the ledger entry becomes failed, Lakeside publishes apx.subscription.failed.v1 to the ops-monitor subscription (never to the failed one), and raises a webhookDeliveryFailed alert. data is a SubscriptionFailure (Part 8 §8.7): the subscription reference plus the facts an operator needs. | F7: GET /webhooks/e8000000-0000-4000-8000-000000000003/deliveries → 200 | G7: =IF(F7="",0,LEN(F7)-LEN(SUBSTITUTE(F7,CHAR(10),""))+1)
A8: EVT-07 | B8: What a failed subscription still allows, and the resume | C8: refusal | D8: APX-EVT-03, APX-SSE-01 | E8: Given e8…0003 is failed. When the city platform tries to narrow its filters, tries to attach to the stream, reads its ledger, and finally resumes. Then 410 subscription-failed on the update (Part 8 §8.1: while failed, the only PATCH accepted is one that sets status: active), 410 on the stream, 200 on the ledger, and 200 on a status-only PATCH — the body is a merge patch, so nothing else has to be resent. | F8: PATCH /webhooks/e8000000-0000-4000-8000-000000000003 → 410 GET /v1/events/stream → 410 GET /webhooks/e8000000-0000-4000-8000-000000000003/deliveries → 200 PATCH /webhooks/e8000000-0000-4000-8000-000000000003 → 200 | G8: =IF(F8="",0,LEN(F8)-LEN(SUBSTITUTE(F8,CHAR(10),""))+1)
A9: EVT-08 | B9: Secret rotation with an overlap window | C9: security | D9: APX-EVT-07, APX-EVT-02 | E9: Given the city's quarterly key rotation. When it PATCHes a new client-supplied secret under a key id it chooses. Then 200 with two activeKeyIds, the secret never echoed, and every delivery during the overlap carrying APX-Key-Id so the receiver verifies against the right key without trying both. The overlap ends when the client retires the old key (EVT-24) or, failing that, 24 hours after the rotation (Part 8 §8.1). A secret with too little entropy is 400 invalid-request pointing at /secret. | F9: PATCH /webhooks/e8000000-0000-4000-8000-000000000003 → 200 PATCH /webhooks/e8000000-0000-4000-8000-000000000003 → 400 | G9: =IF(F9="",0,LEN(F9)-LEN(SUBSTITUTE(F9,CHAR(10),""))+1)
A10: EVT-09 | B10: Key material that never transits the API | C10: happy | D10: APX-EVT-07, APX-EVT-02, APX-EVT-05 | E10: Given city finance's security policy forbids secrets in API bodies. When it subscribes to payment events naming a secretRef exchanged out of band. Then 201 with no secret and an activeKeyIds entry naming the referenced key; deliveries are signed with it and carry the PaymentRecord, whose required place is the binding the filter matches. | F10: POST /webhooks → 201 | G10: =IF(F10="",0,LEN(F10)-LEN(SUBSTITUTE(F10,CHAR(10),""))+1)
A11: EVT-10 | B11: Place binding: what the filter delivers, what it quietly drops | C11: happy | D11: APX-EVT-05, APX-EVT-06 | E11: Given e8…0003 filters to Lakeside with severityFloor: warning. When the night brings an occupancy threshold crossing on level 2 (bound by data.place), a major pay-station alert (bound by data.source.place), a device-state change (bound through the subject device's inventory place), an info alert, and a Harbor Deck alert. Then the first three are delivered and the last two never appear — not in the endpoint's log, not in the ledger. | F11: GET /webhooks/e8000000-0000-4000-8000-000000000003/deliveries → 200 | G11: =IF(F11="",0,LEN(F11)-LEN(SUBSTITUTE(F11,CHAR(10),""))+1)
A12: EVT-11 | B12: Beyond the grant: refused at subscription, dropped at delivery | C12: security | D12: APX-EVT-05, APX-CORE-07, APX-CORE-08 | E12: Given the city token is granted Lakeside only, and ops-monitor (e8…0004) has no places filter at all. When the city asks for a Harbor Deck filter, a token with no apx_places claim asks for any filter, a Harbor Deck occupancy event is published, and a validation statement with no place at all is closed. Then the two subscriptions are refused with insufficient-grant (Part 8 §8.5); the Harbor Deck event is never delivered to ops-monitor; and the unbindable statement event reaches only the auditor's subscription (e8…0007, grant "*") — when in doubt, drop rather than leak. | F12: POST /webhooks → 403 POST /webhooks → 403 | G12: =IF(F12="",0,LEN(F12)-LEN(SUBSTITUTE(F12,CHAR(10),""))+1)
A13: EVT-12 | B13: Wrong scope, wrong purpose, dead token, throttled | C13: security | D13: APX-CORE-07, APX-CORE-05, APX-CORE-10 | E13: Given a BI token carrying only apx.data:read, a city token without apx.lpr:read, an expired token, and a dashboard that polls the ledger every second. When each touches the subscription routes. Then 403 insufficient-scope everywhere; 403 insufficient-scope at creation for a plate-bearing topic the credential could not read synchronously (Part 8 §8.1, Part 9 §9.6(4)); 401 unauthenticated; and 429 with Retry-After. | F13: POST /webhooks → 403 GET /webhooks → 403 GET /webhooks/e8000000-0000-4000-8000-000000000003/deliveries → 403 GET /v1/events/stream → 403 POST /webhooks → 403 GET /webhooks → 401 GET /webhooks/e8000000-0000-4000-8000-000000000003/deliveries → 401 GET /v1/events/stream → 401 GET /webhooks/e8000000-0000-4000-8000-000000000003/deliveries → 429 GET /webhooks → 429 GET /v1/events/stream → 429 | G13: =IF(F13="",0,LEN(F13)-LEN(SUBSTITUTE(F13,CHAR(10),""))+1)
... A19: EVT-18 | B19: Unknown extension keys survive the round trip | C19: edge | D19: APX-CORE-04, APX-EVT-01 | E19: Given the city's integration tags subscriptions with its own routing metadata. When it creates with an apds-ext: key Lakeside has never seen, then PATCHes the topics without mentioning extensions. Then the key is echoed at creation and still present after the update. A key that breaks the §4.3 pattern is refused with 400 invalid-request. | F19: POST /webhooks → 201 PATCH /webhooks/e8000000-0000-4000-8000-000000000010 → 200 POST /webhooks → 400 | G19: =IF(F19="",0,LEN(F19)-LEN(SUBSTITUTE(F19,CHAR(10),""))+1)
A20: EVT-19 | B20: Night shift: the operations feed, end to end | C20: happy | D20: APX-EVT-06, APX-EVT-05 | E20: Given the pay-station fault from EVT-10 at 02:10. When the overnight agent acknowledges the alert, a driver stuck at the exit calls, the resolution context pops on her console, she vends (EVT-13's command), and the interaction is closed. Then ops-monitor receives, in order, apx.alert.status.v1, apx.resolution.context.created.v1, and apx.support.interaction.recorded.v1, each bound to Lakeside. | G20: =IF(F20="",0,LEN(F20)-LEN(SUBSTITUTE(F20,CHAR(10),""))+1)
A21: EVT-20 | B21: Money and enforcement: tolling and violation topics | C21: happy | D21: APX-EVT-06, APX-EVT-05 | E21: Given the city's enforcement subscription (e8…0010) and a tolling subscription on the same endpoint. When a gantry read creates a toll transaction that is later disputed, and an overstay is detected, issued, and paid. Then five envelopes, each carrying the full resource so a consumer never has to call back for it. | G21: =IF(F21="",0,LEN(F21)-LEN(SUBSTITUTE(F21,CHAR(10),""))+1)
A22: EVT-21 | B22: Validations, credentials, and a no-show | C22: happy | D22: APX-EVT-06, APX-EVT-05 | E22: Given ops-monitor holds every APX topic. When the cinema's validation is redeemed at the lane, the cinema program is suspended for non-payment, a monthly card is suspended and then refused at the entry lane, and a reservation passes its grace period. Then five envelopes. The no-show topic's data is ReservationSummary (Part 8 §8.7). | G22: =IF(F22="",0,LEN(F22)-LEN(SUBSTITUTE(F22,CHAR(10),""))+1)
A23: EVT-22 | B23: Valet runner boards and the sensor stream | C23: happy | D23: APX-EVT-06, APX-EVT-05, APX-CORE-10 | E23: Given the valet stand's runner board and the city's LPR analytics each subscribe. When a guest texts for her car, a runner picks it up, and the entry camera reads a plate. Then apx.valet.retrieval.requested.v1, apx.valet.ticket.status.v1, and apx.data.observation.created.v1. The observation topic's data is the APDS ObservationElement, with elementIds as the element binding §8.5 requires (Part 8 §8.7). The plate value rides only under apx.lpr:read (Part 9 §9.6). | G23: =IF(F23="",0,LEN(F23)-LEN(SUBSTITUTE(F23,CHAR(10),""))+1)
A24: EVT-23 | B24: The receiver's clock: the replay window and re-signed retries | C24: edge | D24: APX-EVT-02, APX-EVT-04 | E24: Given the city endpoint comes back at 02:40 during the EVT-05 outage, but its clock is nine minutes slow. When the 02:42:30 retry arrives. Then the receiver, applying the ±5 minute window, rejects it with 400 and the ledger records that code. Once NTP is fixed, the next retry carries a fresh APX-Timestamp and a signature computed over it — the same envelope id, a new APX-Delivery-Id — and is accepted. Part 8 §8.3 makes that re-signing normative: every attempt carries the time of that attempt in APX-Timestamp and a signature over it, with the body unchanged, so an hourly retry is as verifiable as the first attempt. A captured delivery replayed by a third party twenty minutes later fails the same window check and is dropped by the receiver. | F24: GET /webhooks/e8000000-0000-4000-8000-000000000003/deliveries → 200 | G24: =IF(F24="",0,LEN(F24)-LEN(SUBSTITUTE(F24,CHAR(10),""))+1)
A25: EVT-24 | B25: Ending the rotation overlap; the write routes under a bad token | C25: security | D25: APX-EVT-07, APX-CORE-07, APX-CORE-05 | E25: Given every city receiver now verifies with k-2026-09-26-b. When the city retires the old key, and then a mis-deployed job hammers the subscription write routes with an expired token, a read-only token, and no back-off. Then 200 with one activeKeyIds entry (the overlap ended by the client, Part 8 §8.1), and the shared 401 unauthenticated, 403 insufficient-scope, and 429 rate-limited on POST /webhooks, GET/PATCH/DELETE /webhooks/{id}. | F25: PATCH /webhooks/e8000000-0000-4000-8000-000000000003 → 200 POST /webhooks → 401 GET /webhooks/e8000000-0000-4000-8000-000000000003 → 401 PATCH /webhooks/e8000000-0000-4000-8000-000000000003 → 401 DELETE /webhooks/e8000000-0000-4000-8000-000000000003 → 401 GET /webhooks/e8000000-0000-4000-8000-000000000003 → 403 PATCH /webhooks/e8000000-0000-4000-8000-000000000003 → 403 DELETE /webhooks/e8000000-0000-4000-8000-000000000003 → 403 POST /webhooks → 429 GET /webhooks/e8000000-0000-4000-8000-000000000003 → 429 PATCH /webhooks/e8000000-0000-4000-8000-000000000003 → 429 DELETE /webhooks/e8000000-0000-4000-8000-000000000003 → 429 | G25: =IF(F25="",0,LEN(F25)-LEN(SUBSTITUTE(F25,CHAR(10),""))+1)

Sheet apx-lpr
A1: ID | B1: Title | C1: Kind | D1: Annex A rows | E1: Scenario (Given / When / Then) | F1: Exchanges (request → status) | G1: Exchange count | H1: Open spec gap
A2: LPR-01 | B2: Entry camera ingests a read with the APX detail block; the event follows | C2: happy | D2: APX-LPR-01, APX-LPR-02, APX-LPR-03 | E2: Given SYN-1234 drives into entry lane 1 at 08:02 and the camera's engine classifies plate, state, make, model, and colour, each with its own confidence. When the camera posts the native APDS Observation with the apds-ext:apx:lpr-read@1.0 decoration in extensions, the winning values mirrored into observedCredentialId and vehicleAncillaryIdentification, and the still as an Image link. Then the server stores it as a plain Observation (an APDS-only reader sees a valid one), binds it to the lane, and publishes apx.data.observation.created.v1 with the Observation as data and subject referencing it. The APDS schema declares no extensions member on ObservationElement, so the decoration rides as an undeclared additional property (F-LPR-03). | F2: POST /observations → 201 | G2: =IF(F2="",0,LEN(F2)-LEN(SUBSTITUTE(F2,CHAR(10),""))+1)
A3: LPR-02 | B3: Plate to ticket: the lost ticket is found | C3: happy | D3: APX-LPR-01, APX-LPR-03, APX-LPR-04, APX-CORE-10 | E3: Given a transient parker at exit lane 2 with no ticket, and the plate the entry camera read at 08:02. When the agent looks the plate up. Then one LprRead joins the Observation to ticket T-1001 and its session, carries the projected detail with every per-attribute confidence the engine supplied, the accessEvent: entry the LPR system reported, and the still as an access-controlled link. The read names its place and, since the fix for F-LPR-04, the lane and the capturing cameraId. | F3: GET /v1/lpr/reads → 200 | G3: =IF(F3="",0,LEN(F3)-LEN(SUBSTITUTE(F3,CHAR(10),""))+1)
A4: LPR-03 | B4: Ticket to plate: both reads of one visit, and a ticket no camera saw | C4: happy | D4: APX-LPR-01, APX-LPR-02 | E4: Given ticket T-1001 and, later, a ticket T-1077 issued at a lane with no camera. When the console asks for each ticket's reads. Then T-1001 returns the entry read and the exit read taken at 18:40, both bound to the same session and place, in one page, each naming its lane so the console can say which was entry and which exit (F-LPR-04); T-1077 returns an empty page, not an error. | F4: GET /v1/lpr/reads → 200 GET /v1/lpr/reads → 200 | G4: =IF(F4="",0,LEN(F4)-LEN(SUBSTITUTE(F4,CHAR(10),""))+1)
A5: LPR-04 | B5: An older camera with no detail block: nothing is guessed | C5: edge | D5: APX-LPR-03, APX-LPR-04 | E5: Given the ramp camera at Riverside is a first-generation unit that reports a plate string and one overall score, nothing else. When it ingests a read without the decoration. Then the LprRead has no detail at all, so no accessEvent either: the read is simply unknown, and pairing it into a session is the platform's job. The server fills nothing in, and the APDS-native vehicle fields stay empty rather than being filled with defaults. | F5: POST /observations → 201 GET /v1/lpr/reads → 200 | G5: =IF(F5="",0,LEN(F5)-LEN(SUBSTITUTE(F5,CHAR(10),""))+1)
A6: LPR-05 | B6: One frame: the engine cannot call movement, the LPR system still reports the event | C6: edge | D6: APX-LPR-03, APX-LPR-04 | E6: Given a single-frame capture at exit lane 2: the engine saw a rear plate in one frame only (frameReads: 1), so it cannot call motion, and it could not classify colour. The site's LPR system still knows the read came from its exit camera and reports it as an exit. When the console reads it. Then detail.movement is unknown, detail.frameReads is 1, color is absent, and accessEvent is exit exactly as the LPR system reported it. The server infers nothing from the missing geometry and adds nothing to it; laneTravel is the deprecated field's unknown. | F6: GET /v1/lpr/reads → 200 | G6: =IF(F6="",0,LEN(F6)-LEN(SUBSTITUTE(F6,CHAR(10),""))+1)
A7: LPR-06 | B7: Shared driveway in the snow: in through the exit lane, and nothing is flagged | C7: lifecycle | D7: APX-LPR-02, APX-LPR-04, APX-LPR-06 | E7: Given Riverside's entry and exit lanes share one unseparated driveway, and at 07:41 snow covers the lane markings. A grey pickup turns in on the exit side. The exit camera cam-exit-1 faces outward, so a car coming in drives toward it and shows its front plate. When the LPR system reports the read as accessEvent: entry — its own call; APX does not care which lane it was. Then the server stores the read as reported, the platform opens session f1…0741 for the plate, and no alert is raised: APX defines no wrong-way travel (Part 13 §13.3a(6)), so wrongWayTravel is never raised by the server. The observation event carries the reported accessEvent. | F7: POST /observations → 201 GET /v1/lpr/reads → 200 GET /v1/alerts → 200 | G7: =IF(F7="",0,LEN(F7)-LEN(SUBSTITUTE(F7,CHAR(10),""))+1)
A8: LPR-07 | B8: A proper exit: two cameras, front and rear, one passage | C8: happy | D8: APX-LPR-03, APX-LPR-04, APX-LPR-06 | E8: Given Riverside's exit lane carries two cameras: cam-exit-1 faces outward and reads the rear plates of leaving cars, and cam-exit-1f faces inward and reads their front plates. A sedan leaves at 09:12. When both cameras read it; the LPR system gives both reads the same captureGroup and accessEvent: exit, and the front read keeps its second-ranked plate string. Then two LprRead rows come back — one per Observation — sharing a captureGroup, so a consumer counting vehicles counts one exit (§13.3a(6)). alternateReads holds KLM-4478 for the correction flow. Which of the two reads the platform prefers (rear-plate first, at this operator) is the platform's choice, not APX's. | F8: GET /v1/lpr/reads → 200 GET /v1/lpr/reads → 200 | G8: =IF(F8="",0,LEN(F8)-LEN(SUBSTITUTE(F8,CHAR(10),""))+1)
A9: LPR-08 | B9: Candidates for a session, best first, with the engine's second choice | C9: happy | D9: APX-LPR-01, APX-LPR-03, APX-CORE-10 | E9: Given session f1…0031 was opened on a 0.41 entry read of 5VN-4B21, and the customer at exit lane 2 says the plate is SVN-4821. When the agent asks for the session's candidates. Then the fresh 0.97 exit read comes first, then the entry misread with its detail, then the entry engine's own second choice offered as a candidate in its own right (Part 17 §17.5), sharing the entry Observation. Imagery is links that demand the caller's credentials. | F9: GET /v1/lpr/candidates → 200 | G9: =IF(F9="",0,LEN(F9)-LEN(SUBSTITUTE(F9,CHAR(10),""))+1)
A10: LPR-09 | B10: Candidates for a lane since a time, and a session with no reads | C10: happy | D10: APX-LPR-01 | E10: Given the agent does not yet know the session, only the lane the intercom belongs to. When they ask for exit lane 2's candidates since 22:30, and separately for the candidates of a session opened at a camera-less lane. Then the lane query returns the one read taken there in the window, and the camera-less session returns an empty data array with meta.total: 0. | F10: GET /v1/lpr/candidates → 200 GET /v1/lpr/candidates → 200 | G10: =IF(F10="",0,LEN(F10)-LEN(SUBSTITUTE(F10,CHAR(10),""))+1)
A11: LPR-10 | B11: No lookup key at all | C11: refusal | D11: APX-LPR-01, APX-CORE-05 | E11: Given a console that forgot to fill in the search field. When it calls the candidates route with neither session nor lane, and the reads route with neither plate nor ticket. Then both are refused with 400 invalid-request: a plate-keyed surface must never turn into "list every read I can see". (Was F-LPR-05: the reads route declared no 400; it now does, and §13.3 makes one key REQUIRED.) | F11: GET /v1/lpr/candidates → 400 GET /v1/lpr/reads → 400 | G11: =IF(F11="",0,LEN(F11)-LEN(SUBSTITUTE(F11,CHAR(10),""))+1)
A12: LPR-11 | B12: Correct the plate; the reservation links; APDS sees it | C12: lifecycle | D12: APX-LPR-01, APX-LPR-03 | E12: Given the candidates from LPR-08 and a customer who read the plate out loud. When the agent writes SVN-4821 onto session f1…0031 citing the exit Observation. Then 200 with the corrected association; the cross-lookup by the corrected plate now joins the entry Observation (still 5VN-4B21 as observed, never rewritten) to the session, and SessionUpdated is published so a plain APDS client reading /sessions/{id} sees the plate in identifiedCredentials. | F12: PUT /v1/sessions/f1000000-0000-4000-8000-000000000031/plate → 200 GET /v1/lpr/reads → 200 | G12: =IF(F12="",0,LEN(F12)-LEN(SUBSTITUTE(F12,CHAR(10),""))+1)
A13: LPR-12 | B13: The same correction twice, and two agents at once | C13: edge | D13: APX-LPR-01, APX-CORE-05 | E13: Given the console's 200 from LPR-11 was lost to a network blip. When it sends the identical PUT again. Then 200 with the same association and no second SessionUpdated for an unchanged value: PUT is naturally idempotent. Meanwhile a second agent, working from a stale screen, tries to write the old misread back citing the Session version it read (If-Match: "3"); the Session is at version 4, so the write is refused with 409 version-conflict and nothing changes (Part 4 §4.2a, Part 17 §17.5; was F-LPR-08). | F13: PUT /v1/sessions/f1000000-0000-4000-8000-000000000031/plate → 200 PUT /v1/sessions/f1000000-0000-4000-8000-000000000031/plate → 409 | G13: =IF(F13="",0,LEN(F13)-LEN(SUBSTITUTE(F13,CHAR(10),""))+1)
... A36: LPR-35 | B36: Revisions that are refused | C36: security | D36: APX-LPR-04 | E36: Given the revision route of LPR-27. When it is called five wrong ways: a value outside the enum; with an expired token; by the ops console, whose token reads plates but cannot write (apx.lpr:read only); for an Observation id nobody ingested; and by a misbehaving LPR system replaying revisions in a tight loop. Then 400, 401, 403, 404, and 429 in turn, each a registered problem, and nothing is written. | F36: PUT /v1/lpr/reads/f2000000-0000-4000-8000-000000000931/access-event → 400 PUT /v1/lpr/reads/f2000000-0000-4000-8000-000000000931/access-event → 401 PUT /v1/lpr/reads/f2000000-0000-4000-8000-000000000931/access-event → 403 PUT /v1/lpr/reads/f2000000-0000-4000-8000-000000000fff/access-event → 404 PUT /v1/lpr/reads/f2000000-0000-4000-8000-000000000931/access-event → 429 | G36: =IF(F36="",0,LEN(F36)-LEN(SUBSTITUTE(F36,CHAR(10),""))+1)

Sheet apx-permits
A1: ID | B1: Title | C1: Kind | D1: Annex A rows | E1: Scenario (Given / When / Then) | F1: Exchanges (request → status) | G1: Exchange count | H1: Open spec gap
A2: PRM-01 | B2: Check the pool, issue a two-vehicle permit, read it back as stock APDS | C2: happy | D2: APX-PRM-01, APX-PRM-02 | E2: Given Priya Natarajan buys an annual monthly-parker permit for her two cars at the front desk. When the desk console checks the pool, issues the permit with both plates, and the entry lane (which only speaks APDS) reads the assigned right back. Then availability shows three left, the 201 is a native AssignedRight with one CustomerCredential for the holder and one VehicleCredential per plate, the stock read returns the same entity, and availability now shows two left. The rendering follows the §14.2b materialization list: holder → one CustomerCredential, each plate → one VehicleCredential (a CredentialRecord reference, since Lakeside claims apx-credentials), validity → one PlannedUse plus expiry (F-PRM-06 fixed). | F2: GET /v1/permits/pools/e1000000-0000-4000-8000-000000000010/availability → 200 POST /v1/permits/issue → 201 GET /rights/assigned/e2000000-0000-4000-8000-000000000101 → 200 GET /v1/permits/pools/e1000000-0000-4000-8000-000000000010/availability → 200 | G2: =IF(F2="",0,LEN(F2)-LEN(SUBSTITUTE(F2,CHAR(10),""))+1)
A3: PRM-02 | B3: The pool is empty: 409, and the vendor's waitlist | C3: refusal | D3: APX-PRM-01 | E3: Given two more permits went out after PRM-01 and the pool reads zero. When Marcus Bell asks for one. Then 409 pool-exhausted with the counts in detail, and, because Lakeside implements the OPTIONAL waitlist convention, a vendor-extension member on the problem naming his waitlist entry. §14.2 now says plainly that the waitlist is not interoperable and a client must not rely on it (F-PRM-07: won't fix beyond that clarification). | F3: GET /v1/permits/pools/e1000000-0000-4000-8000-000000000010/availability → 200 POST /v1/permits/issue → 409 | G3: =IF(F3="",0,LEN(F3)-LEN(SUBSTITUTE(F3,CHAR(10),""))+1)
A4: PRM-03 | B4: The desk retries after a timeout | C4: edge | D4: APX-PRM-01 | E4: Given the 201 from PRM-01 never reached the desk console. When it retries with the same Idempotency-Key and body, then a colleague reuses the key for a different holder, then a kiosk issues with no key at all. Then 200 with the AssignedRight the key issued (no second slot consumed), 409 idempotency-conflict, and — because the header is optional (making it REQUIRED would break existing clients) — a plain 201 for the keyless kiosk, which is exactly the double-issue a retrying client avoids by sending the key (§14.2; F-PRM-01 fixed). | F4: POST /v1/permits/issue → 200 POST /v1/permits/issue → 409 POST /v1/permits/issue → 201 | G4: =IF(F4="",0,LEN(F4)-LEN(SUBSTITUTE(F4,CHAR(10),""))+1)
A5: PRM-04 | B5: Unknown pool, unknown RightSpecification, unknown holder | C5: refusal | D5: APX-PRM-01 | E5: Given a permit portal with a stale cache of RightSpecification ids and a typo in a holder id. When it asks availability for a RightSpecification that does not exist, issues against it, and issues for a holder that does not exist. Then the availability read is a declared 404 target-not-found; the two issue attempts name nothing through a body Reference, so each is 422 reference-unknown (§14.2a(2); F-PRM-02 fixed — 404 is kept for path ids). | F5: GET /v1/permits/pools/e1000000-0000-4000-8000-0000000000ff/availability → 404 POST /v1/permits/issue → 422 POST /v1/permits/issue → 422 | G5: =IF(F5="",0,LEN(F5)-LEN(SUBSTITUTE(F5,CHAR(10),""))+1)
A6: PRM-05 | B6: A RightSpecification that is not pooled, and a stale spec version | C6: refusal | D6: APX-PRM-01 | E6: Given e1…0011 is Lakeside's event-reservation RightSpecification: it exists, is sold through quotes, and carries no rightPools. When a console asks its availability, tries to issue a permit from it, and then issues from the monthly spec naming version 2 when v3 is current. Then the availability read is the declared 404 ("no pool for this RightSpecification", indistinguishable by type from "no such spec"); the issue against an unpooled spec is 422 request-unprocessable naming the rule (§14.2a(4); F-PRM-03 fixed); the stale version is the declared 409 version-conflict (§14.2a(3)). | F6: GET /rights/specs/e1000000-0000-4000-8000-000000000011 → 200 GET /v1/permits/pools/e1000000-0000-4000-8000-000000000011/availability → 404 POST /v1/permits/issue → 422 POST /v1/permits/issue → 409 | G6: =IF(F6="",0,LEN(F6)-LEN(SUBSTITUTE(F6,CHAR(10),""))+1)
A7: PRM-06 | B7: Wrong scope, and Harbor Deck's pool | C7: security | D7: APX-PRM-01, APX-CORE-06, APX-CORE-07 | E7: Given a BI token with only apx.data:read, and the desk token whose apx_places names Lakeside only. When the BI token reads a pool and issues a permit, and the desk token reads Harbor Deck's pool and issues from it. Then 403 insufficient-scope twice and 403 insufficient-grant twice — the RightSpecification's hierarchyElements place it at Harbor Deck, outside the grant. Both Permits operations now declare 401, 403, and 429 (F-PRM-04 fixed). | F7: GET /v1/permits/pools/e1000000-0000-4000-8000-000000000010/availability → 403 POST /v1/permits/issue → 403 GET /v1/permits/pools/e1000000-0000-4000-8000-000000000020/availability → 403 POST /v1/permits/issue → 403 | G7: =IF(F7="",0,LEN(F7)-LEN(SUBSTITUTE(F7,CHAR(10),""))+1)
A8: PRM-07 | B8: Renewal: a new window, linked through extensions, vendor keys preserved | C8: happy | D8: APX-PRM-01, APX-CORE-09 | E8: Given Priya's permit e2…0101 expires 2027-09-23 and she renews in advance. When the desk re-issues against the same holder with the next window, links the renewal in extensions as §14.2 recommends, and carries a fleet-accounting key the server has never heard of. Then 201 with a new AssignedRight whose extensions echo both keys, and the stock read shows them unchanged (tolerant reader, faithful writer). §14.2 names the link key apds-ext:apx:permit@1.0 (PermitExtension, renews) and PermitIssueRequest now declares extensions (F-PRM-05 fixed). The vendored APDS AssignedRight still declares no container, so the response validates only because APDS does not forbid extra properties (upstream; Part 3 §3.3(8) item). | F8: POST /v1/permits/issue → 201 GET /rights/assigned/e2000000-0000-4000-8000-000000000102 → 200 | G8: =IF(F8="",0,LEN(F8)-LEN(SUBSTITUTE(F8,CHAR(10),""))+1)
A9: PRM-08 | B9: The bakery adds a third van: native PUT, stale version first | C9: lifecycle | D9: APX-PRM-01 | E9: Given Lakeside Bakery's fleet permit e2…0103 (issued earlier today with two vans) is at version 2 after the server materialized the plates. When the fleet manager's tool adds BKR-0003 by writing the whole AssignedRight back through the native route, first with the version it cached (1), then with the current one (2). Then the APDS 409 in the APDS ResponseStatus shape, then 200, and the read shows version 3 with three vehicles. §14.2c now says vehicles change through the native PUT, that the allow-list applies to the new van, and that no pool slot moves (F-PRM-09 fixed). The Part 5 MUST to refuse a stale version with problem version-conflict is still inexpressible on a native route whose 409 is ResponseStatus; that is the cross-cutting native-error-dialect overlay (A7), not a permits change. | F9: PUT /rights/assigned/e2000000-0000-4000-8000-000000000103 → 409 PUT /rights/assigned/e2000000-0000-4000-8000-000000000103 → 200 GET /rights/assigned/e2000000-0000-4000-8000-000000000103 → 200 | G9: =IF(F9="",0,LEN(F9)-LEN(SUBSTITUTE(F9,CHAR(10),""))+1)
A10: PRM-09 | B10: The bakery closes: cancel the permit, and the pool gets a slot back | C10: lifecycle | D10: APX-PRM-01, APX-PRM-02 | E10: Given the bakery shuts in October and asks for a pro-rated refund. When the desk cancels the fleet permit. Then cancellation is the native APDS DELETE, which answers in the APDS shape; the pool afterwards shows one more available, as §14.2c requires, and the refund finds its payment through the AssignedRight's native payments[] transactionID (F-PRM-08 fixed; no dedicated cancel route was added). | F10: DELETE /rights/assigned/e2000000-0000-4000-8000-000000000103 → 200 GET /rights/assigned/e2000000-0000-4000-8000-000000000103 → 404 GET /v1/permits/pools/e1000000-0000-4000-8000-000000000010/availability → 200 | G10: =IF(F10="",0,LEN(F10)-LEN(SUBSTITUTE(F10,CHAR(10),""))+1)
A11: PRM-10 | B11: A permit that has not started yet, seen from the entry lane | C11: lifecycle | D11: APX-PRM-01, APX-PRM-02 | E11: Given the slot freed in PRM-09 goes to Marcus Bell from the waitlist, starting 1 October. When the desk issues it on 24 September and Marcus drives in the same evening, the entry lane runs its stock APDS query for the plate bounded by now. Then 201, an empty list at the lane (denied: not yet valid), and on 1 October the same query returns the right. The lane matches the plate string while the AssignedRight carries a CredentialRecord reference; §14.2b now requires the server to resolve credential_id against the identification string whichever identifier form it materialized (F-PRM-06 fixed). | F11: POST /v1/permits/issue → 201 GET /rights/assigned → 200 GET /rights/assigned → 200 | G11: =IF(F11="",0,LEN(F11)-LEN(SUBSTITUTE(F11,CHAR(10),""))+1)
A12: PRM-11 | B12: Malformed issue: no holder, and a credential type the spec does not allow | C12: refusal | D12: APX-PRM-01 | E12: Given a portal integration under development. When it posts an issue with no holder, and another with an rfid credential against a RightSpecification whose credentials list allows only licensePlate. Then the first is the declared 400 invalid-request; the second is 422 request-unprocessable naming the allow-list rule (§14.2a(5); F-PRM-02, F-PRM-03 fixed). credentialType stays a free string in the schema — narrowing it to CredentialTypeEnum would break existing clients — and a non-enum value is 400 invalid-request by the §14.2a(1) field rule, as the third attempt shows. | F12: POST /v1/permits/issue → 400 POST /v1/permits/issue → 422 POST /v1/permits/issue → 400 | G12: =IF(F12="",0,LEN(F12)-LEN(SUBSTITUTE(F12,CHAR(10),""))+1)
A13: PRM-12 | B13: A plate that is already on someone else's active permit | C13: edge | D13: APX-PRM-01 | E13: Given Priya sold PRY-2202 to Marcus and did not tell the garage. When Marcus's permit is issued with that plate while Priya's e2…0101 still carries it. Then Lakeside's policy is one plate, one permit, so it refuses with 409 credential-identification-in-use, which §14.2a(6) licenses whether or not the server claims apx-credentials (F-PRM-03 fixed); a server that allows the plate on two permits says so in its ICS. | F13: POST /v1/permits/issue → 409 | G13: =IF(F13="",0,LEN(F13)-LEN(SUBSTITUTE(F13,CHAR(10),""))+1)
A14: PRM-13 | B14: What the fabric says when a permit is issued | C14: happy | D14: APX-PRM-01 | E14: Given a subscriber on the native AssignedRightCreated topic (the permit profile adds no topic of its own). When PRM-01's permit is issued. Then one envelope with the AssignedRight as data. Part 8 says data is the APDS EventData shape, but the bundle does not carry EventData or EventTypeEnum, so the closest checkable statement is "data is an AssignedRight" (F-PRM-11, owned by apx-events). §14.2c now names apx.permits.pool.availability.v1 for pool-count changes (F-PRM-10; the apx-topics registry entry is pending). The subscriber's first 2xx is lost and the delivery is retried two seconds later with the identical envelope (same id, Part 8 §8.2): the envelope is checked on the first delivery and its data on the retry. | G14: =IF(F14="",0,LEN(F14)-LEN(SUBSTITUTE(F14,CHAR(10),""))+1)
A15: PRM-14 | B15: One RightSpecification, two pools: which one is "availability"? | C15: edge | D15: APX-PRM-01 | E15: Given Lakeside's Q4 monthly spec e1…0012 carries one RightPool for October (80 issued of 100) and one for November (12 of 100), the way APDS models per-period pools. When the sales portal asks availability with no period, then with at= for November, then by pool id. Then the first answer is the pool whose validity contains now (October), the second and third are November, and each names the selected pool and its validity; capacity is distributedAssignedRights + availableAssignedRights of that pool (§14.2; F-PRM-12 fixed). | F15: GET /rights/specs/e1000000-0000-4000-8000-000000000012 → 200 GET /v1/permits/pools/e1000000-0000-4000-8000-000000000012/availability → 200 GET /v1/permits/pools/e1000000-0000-4000-8000-000000000012/availability → 200 GET /v1/permits/pools/e1000000-0000-4000-8000-000000000012/availability → 200 | G15: =IF(F15="",0,LEN(F15)-LEN(SUBSTITUTE(F15,CHAR(10),""))+1)
A16: PRM-15 | B16: Midnight renewal batch: throttled, then a dead token | C16: edge | D16: APX-CORE-05 | E16: Given a permit portal renews 400 permits in a burst at 00:00. When it exceeds the write rate limit, and later keeps going on an expired token. Then 429 with Retry-After on both operations and 401 on both, all declared, with problem type unauthenticated (F-PRM-04 fixed). | F16: POST /v1/permits/issue → 429 GET /v1/permits/pools/e1000000-0000-4000-8000-000000000010/availability → 429 POST /v1/permits/issue → 401 GET /v1/permits/pools/e1000000-0000-4000-8000-000000000010/availability → 401 | G16: =IF(F16="",0,LEN(F16)-LEN(SUBSTITUTE(F16,CHAR(10),""))+1)

Sheet apx-reservations
A1: ID | B1: Title | C1: Kind | D1: Annex A rows | E1: Scenario (Given / When / Then) | F1: Exchanges (request → status) | G1: Exchange count | H1: Open spec gap
A2: RSV-01 | B2: Quote Friday night before booking it | C2: happy | D2: APX-RSV-01, APX-CORE-01 | E2: Given Priya wants Lakeside Garage 18:00–23:00 on concert Friday. When ParkAhead asks for a native APDS quote against the evening right specification. Then 200 with one QuoteRightResponse carrying an option priced at USD 24.00 that expires in thirty minutes. The vendored APDS POST /quotes declares no request body at all (F-RSV-01), and its Identifiers block has a required-key typo, so the option omits it (F-RSV-03). | F2: POST /quotes → 200 | G2: =IF(F2="",0,LEN(F2)-LEN(SUBSTITUTE(F2,CHAR(10),""))+1)
A3: RSV-02 | B3: Book: an AssignedRight wearing the reservation extension | C3: happy | D3: APX-RSV-01, APX-CORE-01, APX-CORE-02, APX-CORE-04 | E3: Given Priya accepted the quote. When ParkAhead creates a native AssignedRight with her plate on file, a plannedUses entry, and the apds-ext:apx:reservation@1.0 extension in confirmed. Then the native 201 ResponseStatus names the id, a plain APDS read returns the full right with the extension intact, and AssignedRightCreated is published with the right as data. Public scenarios 05 and 06 now draw the same shapes (201 ResponseStatus, then a read-back; rightHolder.credentials[]; was F-RSV-04). AssignedRight itself declares no extensions property (F-RSV-05, upstream). The extension's planned times mirror plannedUses[0], which Part 14 §14.1 now makes authoritative (was F-RSV-10). | F3: POST /rights/assigned → 201 GET /rights/assigned/e2000000-0000-4000-8000-000000000101 → 200 | G3: =IF(F3="",0,LEN(F3)-LEN(SUBSTITUTE(F3,CHAR(10),""))+1)
A4: RSV-03 | B4: Book straight from the quote reference | C4: edge | D4: APX-RSV-01, APX-CORE-01 | E4: Given the same quote, and a platform that prefers the APDS "reference the option" create shape. When it posts a ReferenceToQuote naming the response and the option. Then the server would create the right from the quote, but the vendored schema cannot validate the body: ReferenceToQuote is a oneOf of two identical branches, so every body matches both (F-RSV-02). There is also nowhere in this shape to put the reservation extension, so the server must infer plannedStart/plannedEnd from the quote. | F4: POST /rights/assigned → 201 | G4: =IF(F4="",0,LEN(F4)-LEN(SUBSTITUTE(F4,CHAR(10),""))+1) | H4: F-RSV-02
A5: RSV-04 | B5: Book refused: colliding id, missing holder | C5: refusal | D5: APX-CORE-03, APX-RSV-01 | E5: Given two broken retries. When one re-posts Priya's booking with the id that already exists, and one omits rightHolder. Then the native route answers 409 and 400 in the APDS ResponseStatus shape, which Part 12 §12.1 permits on native routes; nothing is created. | F5: POST /rights/assigned → 409 POST /rights/assigned → 400 | G5: =IF(F5="",0,LEN(F5)-LEN(SUBSTITUTE(F5,CHAR(10),""))+1)
A6: RSV-05 | B6: Amend before arrival: dinner runs long | C6: lifecycle | D6: APX-RSV-01, APX-DATA-02 | E6: Given Priya's confirmed reservation at version 1. When ParkAhead pushes the end from 23:00 to 01:00 with a native PUT carrying the version it read. Then 200, the read shows version 2 in amended, and AssignedRightUpdated carries the new state. The body's version is the version the client last read (Part 4 §4.2a, cited from Part 14 §14.1 step 3; was F-RSV-07). | F6: PUT /rights/assigned/e2000000-0000-4000-8000-000000000101 → 200 GET /rights/assigned/e2000000-0000-4000-8000-000000000101 → 200 | G6: =IF(F6="",0,LEN(F6)-LEN(SUBSTITUTE(F6,CHAR(10),""))+1)
A7: RSV-06 | B7: Two amendments race: the stale one loses | C7: refusal | D7: APX-DATA-02, APX-CORE-05 | E7: Given a second ParkAhead worker still holding version 1 of Priya's reservation. When it PUTs its own amendment. Then 409: the native route answers in the APDS ResponseStatus shape, which is what its OpenAPI declares. Part 5 §5.1 mandates problem version-conflict for exactly this case and Part 12 §12.1 says native routes SHOULD honour Accept: application/problem+json, but the vendored route declares no such content, so the problem+json variant is a gap (F-RSV-08). | F7: PUT /rights/assigned/e2000000-0000-4000-8000-000000000101 → 409 PUT /rights/assigned/e2000000-0000-4000-8000-000000000101 → 409 | G7: =IF(F7="",0,LEN(F7)-LEN(SUBSTITUTE(F7,CHAR(10),""))+1)
A8: RSV-07 | B8: Check-in: the entry camera reads the plate | C8: lifecycle | D8: APX-RSV-01, APX-RSV-02 | E8: Given Friday 18:04 and the entry camera reads SYN-1234. When the PARCS matches it to the plate credential on Priya's reservation, opens the gate, and creates the native Session whose segment references the AssignedRight. Then 201, the reservation transitions to checkedIn with checkInSession set (§14.1 rule 5), and AssignedRightUpdated says so. The plate is the link; no APX call was needed. | F8: POST /sessions → 201 GET /rights/assigned/e2000000-0000-4000-8000-000000000101 → 200 | G8: =IF(F8="",0,LEN(F8)-LEN(SUBSTITUTE(F8,CHAR(10),""))+1)
A9: RSV-08 | B9: Set-time reservation extended mid-stay | C9: lifecycle | D9: APX-RSV-01 | E9: Given Marisol's set-time reservation e2…0103 (Tuesday 06:00–18:00, plate SYN-5150), checked in at 05:52 as session f1…0202, now at version 3. When at 16:40 her return flight slips and ParkAhead prices the extra hours with the stock APDS session-extension quote, then moves plannedEnd with a change-mode PUT. Then the quote honours 22:00, the PUT is 200, and the reservation STAYS checkedIn — after check-in only the planned times move (§14.1 rule 3). Part 14 §14.1 step 3 now requires a change-mode amend to keep the AssignedRight's required members until a change-mode schema exists (was F-RSV-06; the general schema is F-DATA-02), so the body below validates; the quote request has the F-RSV-01 gap. | F9: POST /quotes → 200 PUT /rights/assigned/e2000000-0000-4000-8000-000000000103 → 200 GET /rights/assigned/e2000000-0000-4000-8000-000000000103 → 200 | G9: =IF(F9="",0,LEN(F9)-LEN(SUBSTITUTE(F9,CHAR(10),""))+1)
A10: RSV-09 | B10: The third extension is declined | C10: refusal | D10: APX-RSV-01 | E10: Given Marisol at 21:50 asks to keep the car overnight until 09:00. When ParkAhead quotes the extension. Then the quote comes back declined with noExtensionPossible and revisedEndTime still at the committed 22:00 — a decline never shrinks what was granted. ParkAhead does not PUT; the reservation runs out at its twice-extended time. | F10: POST /quotes → 200 | G10: =IF(F10="",0,LEN(F10)-LEN(SUBSTITUTE(F10,CHAR(10),""))+1)
A11: RSV-10 | B11: Cancel: by DELETE, by state, and too late | C11: lifecycle | D11: APX-RSV-01 | E11: Given Priya also booked next week twice by mistake (e2…0108 and e2…0109, both confirmed). When ParkAhead deletes one and sets the other to cancelled with a cancelTime on the planned use — both paths §14.1 rule 4 allows. Then 200 for each, the deleted one reads 404 and publishes AssignedRightDeleted, the cancelled one reads back in cancelled. Deleting the reservation Priya has already checked in on is refused with a native 409: the §14.1 transition table (cancel after check-in is illegal) and the registered problem type reservation-transition-illegal now cover it (was F-RSV-09); the native route still answers ResponseStatus, since its problem+json variant waits on the F-RSV-08 overlay. | F11: DELETE /rights/assigned/e2000000-0000-4000-8000-000000000108 → 200 GET /rights/assigned/e2000000-0000-4000-8000-000000000108 → 404 PUT /rights/assigned/e2000000-0000-4000-8000-000000000109 → 200 DELETE /rights/assigned/e2000000-0000-4000-8000-000000000101 → 409 | G11: =IF(F11="",0,LEN(F11)-LEN(SUBSTITUTE(F11,CHAR(10),""))+1)
A12: RSV-11 | B12: Theo never shows, then shows up late | C12: lifecycle | D12: APX-RSV-01, APX-RSV-03 | E12: Given Theo's reservation e2…0102 for 18:00 and Lakeside's sixty-minute grace period (operator policy, §14.1 rule 6). When the 19:00 sweep finds no check-in. Then the reservation transitions to noShow and apx.reservation.noshow.v1 is published with a ReservationSummary as data (Part 14 §14.1 step 6 now names it; the registry text is with the integrator), and the lapse instant was visible all along as the server-set noShowAfter (was F-RSV-11). At 19:40 Theo arrives, takes a ticket, and the agent tries to link the no-show right to his drive-up session: 409 right-not-linkable, which §14.1b now lists for noShow and cancelled rights (was F-RSV-09). | F12: GET /rights/assigned/e2000000-0000-4000-8000-000000000102 → 200 PUT /v1/sessions/f1000000-0000-4000-8000-000000000208/assigned-right → 409 | G12: =IF(F12="",0,LEN(F12)-LEN(SUBSTITUTE(F12,CHAR(10),""))+1)
A13: RSV-12 | B13: Illegal transitions the state machine must refuse | C13: refusal | D13: APX-RSV-01, APX-RSV-03 | E13: Given Theo's noShow right and Priya's cancelled e2…0109. When a platform tries to PUT the no-show back to confirmed, tries to amend the cancelled one, and an agent tries to check the cancelled one in through the explicit link. Then two native 409s and one 409 right-not-linkable. Part 14 §14.1 now has the transition table (confirmed → amended | checkedIn | cancelled | noShow, amended → amended | checkedIn | cancelled | noShow, checkedIn moves only its planned times, cancelled and noShow are terminal) and Part 12 registers reservation-transition-illegal (was F-RSV-09); the native 409s stay ResponseStatus until the F-RSV-08 overlay lets them carry it. | F13: PUT /rights/assigned/e2000000-0000-4000-8000-000000000102 → 409 PUT /rights/assigned/e2000000-0000-4000-8000-000000000109 → 409 PUT /v1/sessions/f1000000-0000-4000-8000-000000000204/assigned-right → 409 | G13: =IF(F13="",0,LEN(F13)-LEN(SUBSTITUTE(F13,CHAR(10),""))+1)
A14: RSV-13 | B14: Screen-pop: the caller's last reservations, by plate | C14: happy | D14: APX-RSV-02, APX-CORE-02 | E14: Given Priya calls the intercom at exit lane 2 and the camera has her plate. When the console asks for her recent reservations by plate. Then 200 with up to ten summaries, newest planned start first, mixed states — the cancelled and no-show history is the dispute context. A plain APDS client can get the same rights through the native list with the credential filter and sees ordinary assigned rights. The plate key takes the optional country/stateProvince qualifiers (Part 14 §14.1a(4); was F-RSV-14), which the console fills from the LPR read. | F14: GET /v1/reservations/recent → 200 GET /rights/assigned → 200 | G14: =IF(F14="",0,LEN(F14)-LEN(SUBSTITUTE(F14,CHAR(10),""))+1)
A15: RSV-14 | B15: The aggregator: local holder ids, re-minted place, plate as the join | C15: happy | D15: APX-RSV-02, APX-CORE-11 | E15: Given Lakeside moved behind Metro Parking Hub, which fronts several garages and had to re-mint Lakeside's place id to b1…00a1 (Part 18 §18.2). When ParkAhead, still holding Priya's Lakeside holder id, asks the hub by holder; then asks by plate scoped to the new place id; then reads the place. Then the holder lookup returns an empty list (the id is local to the old endpoint, §14.1a, and an unknown holder is not an error), the plate lookup finds her, and the HierarchyElement carries the old id in operatorDefinedReference. | F15: GET /v1/reservations/recent → 200 GET /v1/reservations/recent → 200 GET /places/b1000000-0000-4000-8000-0000000000a1 → 200 | G15: =IF(F15="",0,LEN(F15)-LEN(SUBSTITUTE(F15,CHAR(10),""))+1)
A16: RSV-15 | B16: Recent lookup refused: no key, and a window it does not have | C16: refusal | D16: APX-RSV-02, APX-CORE-05 | E16: Given a console that sends the lookup without any key, and a dispute desk that wants "her reservations in June". When the first calls with no plate or holder, and the second adds from/to — first inverted, then correct, with a state filter. Then 400 invalid-request for the missing key and for the inverted window, and 200 for June's cancelled bookings (the operation now takes from, to, and state, and both keys together intersect; was F-RSV-13). | F16: GET /v1/reservations/recent → 400 GET /v1/reservations/recent → 400 GET /v1/reservations/recent → 200 | G16: =IF(F16="",0,LEN(F16)-LEN(SUBSTITUTE(F16,CHAR(10),""))+1)
... A25: RSV-24 | B25: Re-pointing done right: unlink, then link | C25: lifecycle | D25: APX-RSV-03, APX-CORE-05, APX-CORE-06, APX-CORE-07 | E25: Given RSV-18's session f1…0203, linked to Dev's e2…0104 at Session version 2, and his duplicate booking e2…0112 that he wants applied instead. When the agent unlinks with a reason and If-Match: "2", repeats the unlink (lost response), links e2…0112, and a second console still on version 2 tries to link. Then 200 with unlinkedRight (the segment is back on the drive-up right and e2…0104 returns to confirmed, checkInSession cleared), a no-op 200 without unlinkedRight, 200 for the new link, and 409 version-conflict. The unlink refuses a body without reason (400), an unknown session (404), a stale version (409), a settled session (422), the wrong scope (403), a dead token (401), and a burst (429) — Part 14 §14.1b (was F-RSV-16). | F25: POST /v1/sessions/f1000000-0000-4000-8000-000000000203/assigned-right/unlink → 200 POST /v1/sessions/f1000000-0000-4000-8000-000000000203/assigned-right/unlink → 200 GET /rights/assigned/e2000000-0000-4000-8000-000000000104 → 200 PUT /v1/sessions/f1000000-0000-4000-8000-000000000203/assigned-right → 200 PUT /v1/sessions/f1000000-0000-4000-8000-000000000203/assigned-right → 409 POST /v1/sessions/f1000000-0000-4000-8000-000000000203/assigned-right/unlink → 400 POST /v1/sessions/f1000000-0000-4000-8000-0000000000ff/assigned-right/unlink → 404 POST /v1/sessions/f1000000-0000-4000-8000-000000000203/assigned-right/unlink → 409 POST /v1/sessions/f1000000-0000-4000-8000-000000000201/assigned-right/unlink → 422 POST /v1/sessions/f1000000-0000-4000-8000-000000000203/assigned-right/unlink → 403 POST /v1/sessions/f1000000-0000-4000-8000-000000000203/assigned-right/unlink → 401 POST /v1/sessions/f1000000-0000-4000-8000-000000000203/assigned-right/unlink → 429 | G25: =IF(F25="",0,LEN(F25)-LEN(SUBSTITUTE(F25,CHAR(10),""))+1)

Sheet apx-resolution
A1: ID | B1: Title | C1: Kind | D1: Annex A rows | E1: Scenario (Given / When / Then) | F1: Exchanges (request → status) | G1: Exchange count | H1: Open spec gap
A2: RES-01 | B2: The intercom at exit lane 2 becomes a context before anyone speaks | C2: happy | D2: APX-RES-01, APX-RES-03, APX-RES-05 | E2: Given J. Smith, a monthly parker with a $185.00 balance hold, is denied at exit lane 2 and presses the intercom; the call platform maps that intercom to the lane on its own side. When it posts the lane with an opaque interactionId and a freshly minted correlationId. Then 201 with a full context: the issue classified, the live lane status, the account section (the token holds apx.accounts:read), two courtesy exits already in recentOverrides, and three policy decisions — a payment link allowed, a courtesy exit refused with a machine-readable reason, and a gate vend gated behind a supervisor. recommendedAction names one of the allowed ones. Each OverrideRecord now says which agent granted the earlier courtesy and why, copied from the Command (was F-RES-13). | F2: POST /v1/resolution/contexts → 201 | G2: =IF(F2="",0,LEN(F2)-LEN(SUBSTITUTE(F2,CHAR(10),""))+1)
A3: RES-02 | B3: Preloading: the server creates the context on the second denial | C3: lifecycle | D3: APX-RES-01 | E3: Given M. Rivera badges twice at entry lane 1 and is denied twice. When the PARCS creates a context on its own (§17.2 preloading) and publishes apx.resolution.context.created.v1, bound to the place per Part 8 §8.5 by data.place. Then the agent console receives the envelope before the call is answered, reads the context by id, and gets the same version: 1 because nothing material changed. | F3: GET /v1/resolution/contexts/e5000000-0000-4000-8000-000000000002 → 200 | G3: =IF(F3="",0,LEN(F3)-LEN(SUBSTITUTE(F3,CHAR(10),""))+1)
A4: RES-03 | B4: "I lost my ticket": a plate over chat finds the entry | C4: happy | D4: APX-RES-01, APX-RES-05 | E4: Given a driver on the web chat says they lost their ticket and types their plate; the chat platform knows the garage but no lane. When it posts plate + place. Then the entry LPR read resolves the open session, so no lost-ticket fee is needed: policy allows a payment link on the session for the true amount and lists nothing physical, because no lane is known. laneStatus is absent — graceful degradation, not an error. | F4: POST /v1/resolution/contexts → 201 | G4: =IF(F4="",0,LEN(F4)-LEN(SUBSTITUTE(F4,CHAR(10),""))+1)
A5: RES-04 | B5: Paid ticket, gate did not open: the AI agent presses one button and claims no more than the sensor confirms | C5: happy | D5: APX-RES-03, APX-RES-05 | E5: Given a driver at exit lane 2 reads a ticket number to the voice bot after a paid ticket failed to vend. When the bot posts ticketNumber + place. Then the context shows the ticket paid in full and the gate healthy, policy allows a single vendGate and refuses a hold-open, and the bot executes exactly the recommended action with agentType: ai. At confirmationLevel: accepted the bot may say only "I have sent the open command"; after the poll shows physicallyConfirmed it may say "the gate is open". | F5: POST /v1/resolution/contexts → 201 POST /v1/commands → 202 GET /v1/commands/d1000000-0000-4000-8000-000000000204 → 200 | G5: =IF(F5="",0,LEN(F5)-LEN(SUBSTITUTE(F5,CHAR(10),""))+1)
A6: RES-05 | B6: Card declined at the pay-in-lane terminal: the payment link is the way out | C6: happy | D6: APX-RES-01, APX-RES-03, APX-RES-05 | E6: Given a transient parker's card is declined twice at terminal c1…0003; the terminal's help button is inventoried, so the platform anchors the interaction to the device. When the agent sends a payment link for the ticket, the console retries after a timeout with the same key, a bug reuses the key with a different body, a client sends an unsupported channel, and a read-only token tries. Then 201, 200 with the ORIGINAL link, 409 idempotency-conflict, 400 invalid-request (registered since F-RES-01), and 403 insufficient-scope. The link never carries a PAN; sentTo is masked. | F6: POST /v1/resolution/contexts → 201 POST /v1/payment-links → 201 POST /v1/payment-links → 200 POST /v1/payment-links → 409 POST /v1/payment-links → 400 POST /v1/payment-links → 403 | G6: =IF(F6="",0,LEN(F6)-LEN(SUBSTITUTE(F6,CHAR(10),""))+1)
A7: RES-06 | B7: "The restaurant validated me": a ticket number, a provider check, a command | C7: happy | D7: APX-RES-03, APX-RES-05 | E7: Given a driver at exit lane 2 sees $14.00 due and claims a Harbor Restaurant validation. When the agent posts the ticket number and the lane. Then the context shows an unvalidated ticket, policy allows applyValidation and refuses a vend, and the execution descriptor sends the agent to the command plane with the context and correlation id attached. The AI classifies and proposes; the server decided. | F7: POST /v1/resolution/contexts → 201 POST /v1/commands → 202 | G7: =IF(F7="",0,LEN(F7)-LEN(SUBSTITUTE(F7,CHAR(10),""))+1)
A8: RES-07 | B8: Rate dispute: the policy decisions bind the command plane | C8: refusal | D8: APX-RES-03, APX-RES-04 | E8: Given a context whose policy says pushRate requires supervisor approval, holdGateOpen is not allowed, and closeLane is not listed at all. When the agent pushes the corrected table without approval, then with it; the AI agent tries the hold-open; and a console sends a closeLane naming the context. Then 403 approval-required, 202, 403 action-not-allowed, and — for the unlisted type — 403 action-not-allowed, which Part 17 §17.3 now requires: not offered by the named context is not allowed (was F-RES-11). | F8: POST /v1/resolution/contexts → 201 POST /v1/commands → 403 POST /v1/commands → 202 POST /v1/commands → 403 POST /v1/commands → 403 | G8: =IF(F8="",0,LEN(F8)-LEN(SUBSTITUTE(F8,CHAR(10),""))+1)
A9: RES-08 | B9: "It says I'm already inside": passback read, reset, re-read | C9: happy | D9: APX-RES-07, APX-RES-01, APX-RES-05 | E9: Given M. Rivera's credential is recorded inside because yesterday's exit was attendant-waved and never read. When the platform posts the credential and the entry lane, the console refreshes the passback overlay on its own read, the agent issues resetPassback, and re-reads. Then the context's passback section says why, policy allows the reset and refuses a blind vend, and the overlay returns to normal with no override counted against courtesy policy. | F9: POST /v1/resolution/contexts → 201 GET /v1/credentials/c3000000-0000-4000-8000-000000000002/passback → 200 POST /v1/commands → 202 GET /v1/credentials/c3000000-0000-4000-8000-000000000002/passback → 200 | G9: =IF(F9="",0,LEN(F9)-LEN(SUBSTITUTE(F9,CHAR(10),""))+1)
A10: RES-09 | B10: forceOut, forceIn, and a credential nobody tracks | C10: lifecycle | D10: APX-RES-07 | E10: Given a night of construction egress where the attendant waved out forty monthly cars. When the supervisor forces one credential outside after the fact, later forces it inside when the driver is physically parked and the entry read was missed, and the console asks for the passback status of a transient credential the site does not track, and of an id that does not exist. Then 202, 200 outside, 202, 200 state: unknown for the untracked credential, and 404 only for the unknown id (Part 17 §17.8; was F-RES-07). | F10: POST /v1/commands → 202 GET /v1/credentials/c3000000-0000-4000-8000-000000000001/passback → 200 POST /v1/commands → 202 GET /v1/credentials/c3000000-0000-4000-8000-0000000000fe/passback → 200 GET /v1/credentials/c3000000-0000-4000-8000-0000000000ff/passback → 404 | G10: =IF(F10="",0,LEN(F10)-LEN(SUBSTITUTE(F10,CHAR(10),""))+1)
A11: RES-10 | B11: "I prepaid but it wants full price": candidates, correction, re-read | C11: happy | D11: APX-RES-08, APX-RES-01, APX-RES-05 | E11: Given the entry camera read SVN-4821 as 5VN-4B21 at 0.41, so the reservation never linked. When the platform posts the lane plus the reservation code the customer reads out, the agent lists the lane's candidates since the exit approach, writes the top one to the session citing its Observation, and re-reads the context. Then the context names the unlinked reservation and allows only the plate correction; the candidates come best-first with access-controlled imagery; the PUT returns the corrected association; and the re-read is version: 2 with access granted and nothing left to do. | F11: POST /v1/resolution/contexts → 201 GET /v1/lpr/candidates → 200 PUT /v1/sessions/c4000000-0000-4000-8000-000000000031/plate → 200 GET /v1/resolution/contexts/e5000000-0000-4000-8000-000000000010 → 200 | G11: =IF(F11="",0,LEN(F11)-LEN(SUBSTITUTE(F11,CHAR(10),""))+1)
A12: RES-11 | B12: No plate on the session: the engine's second choice was the right one | C12: happy | D12: APX-RES-08 | E12: Given a session opened with a plate the engine could not settle on; the back-office console already holds the session id. When it resolves a context by session alone, the agent lists candidates by session, sees the winning read carried alternateReads in its Part 13 §13.3a detail, and writes the alternate; then a console asks for candidates with neither session nor lane, a BI token without apx.lpr:read asks, and someone corrects a session that does not exist. Then 201 classified plateUnresolved, 200, 200, 400 invalid-request (registered since F-RES-01), 403 insufficient-scope, 404 target-not-found. | F12: POST /v1/resolution/contexts → 201 GET /v1/lpr/candidates → 200 PUT /v1/sessions/c4000000-0000-4000-8000-000000000041/plate → 200 GET /v1/lpr/candidates → 400 GET /v1/lpr/candidates → 403 PUT /v1/sessions/c4000000-0000-4000-8000-0000000000ff/plate → 404 | G12: =IF(F12="",0,LEN(F12)-LEN(SUBSTITUTE(F12,CHAR(10),""))+1)
A13: RES-12 | B13: Barcode-only reservation: the explicit session ↔ right link | C13: happy | D13: APX-RES-01, APX-RES-05 | E13: Given Harbor Restaurant's shuttle lot sells barcode reservations and the customer's code was never scanned at entry, so no plate can carry the link. When the context resolves the reservation from the code and the agent applies the link with the code as evidence. Then policy lists put-apx-v1-sessions-id-assigned-right as the domain action, the PUT returns the applied link, and the prepaid rate follows from the implementation's normal rating. | F13: POST /v1/resolution/contexts → 201 PUT /v1/sessions/c4000000-0000-4000-8000-000000000032/assigned-right → 200 | G13: =IF(F13="",0,LEN(F13)-LEN(SUBSTITUTE(F13,CHAR(10),""))+1)
... A29: RES-28 | B29: The way out offered on a channel the place does not run | C29: refusal | D29: APX-ACC-04 | E29: Given a declined card at the exit, and a resolution context that offers a payment link. When the agent asks for the link by fax, a channel Lakeside does not run. Then 422 request-unprocessable, with the supported channels in detail, so the agent can offer SMS instead. | F29: POST /v1/payment-links → 422 | G29: =IF(F29="",0,LEN(F29)-LEN(SUBSTITUTE(F29,CHAR(10),""))+1)

Sheet apx-tolling
A1: ID | B1: Title | C1: Kind | D1: Annex A rows | E1: Scenario (Given / When / Then) | F1: Exchanges (request → status) | G1: Exchange count | H1: Open spec gap
A2: TOL-01 | B2: 07:14, a transponder passes the gantry | C2: happy | D2: APX-TOL-01, APX-CORE-03 | E2: Given gantry hc-01 ingested a transponder hit and a plate read as two Observations. When the gantry bridge posts a toll transaction that references both, the credential, and the flat 2-axle peak price, under a key derived from the gantry, the read time, and its sequence number. Then 201 with the transaction already priced (pricing is synchronous here), a two-entry audit trail, and apx.tolling.transaction.created.v1 published with the transaction as data. | F2: POST /v1/tolling/transactions → 201 | G2: =IF(F2="",0,LEN(F2)-LEN(SUBSTITUTE(F2,CHAR(10),""))+1)
A3: TOL-02 | B3: The uplink flapped: the gantry re-sends the same read | C3: edge | D3: APX-TOL-01 | E3: Given the 201 from TOL-01 never reached the gantry bridge, and the bridge re-sends everything it buffered once the uplink returns. When the identical body arrives under the identical key, a minute later. Then 200 with the transaction the key created, e9…0801, in its current representation (still version 2 here): not a new transaction, not a second charge (Part 4 §4.2a, §15.2; F-TOL-12 fixed). | F3: POST /v1/tolling/transactions → 200 | G3: =IF(F3="",0,LEN(F3)-LEN(SUBSTITUTE(F3,CHAR(10),""))+1)
A4: TOL-03 | B4: Same key, different read | C4: refusal | D4: APX-TOL-01, APX-CORE-05 | E4: Given a firmware bug in the gantry bridge reuses the sequence number after a reboot. When the 07:52 plate-only passage is posted under the 07:14 key. Then 409 idempotency-conflict; the second passage is not recorded and the bridge must re-key it. | F4: POST /v1/tolling/transactions → 409 | G4: =IF(F4="",0,LEN(F4)-LEN(SUBSTITUTE(F4,CHAR(10),""))+1)
A5: TOL-04 | B5: Malformed ingests: no key, no toll point, throttled | C5: refusal | D5: APX-TOL-01, APX-CORE-05 | E5: Given three misbehaving gantry bridges. When one posts without Idempotency-Key, one posts a body with no tollPoint, and one replays its whole 40-minute buffer in a burst. Then 400 idempotency-key-required, 400 invalid-request for the invalid transaction (F-TOL-05 fixed), and 429 with Retry-After so the buffer drains at a rate the server can take. | F5: POST /v1/tolling/transactions → 400 POST /v1/tolling/transactions → 400 POST /v1/tolling/transactions → 429 | G5: =IF(F5="",0,LEN(F5)-LEN(SUBSTITUTE(F5,CHAR(10),""))+1)
A6: TOL-05 | B6: Settled against the account that night | C6: happy | D6: APX-TOL-01 | E6: Given the nightly billing run charged the holder's account through the Part 13 payment surface and holds a PaymentRecord. When it attaches that reference to e9…0801. Then 200 with the transaction paid at version 3, the history naming the batch, and apx.tolling.transaction.status.v1 published. The toll record holds a reference; it never becomes a parallel ledger. | F6: POST /v1/tolling/transactions/e9000000-0000-4000-8000-000000000801/payment → 200 | G6: =IF(F6="",0,LEN(F6)-LEN(SUBSTITUTE(F6,CHAR(10),""))+1)
A7: TOL-06 | B7: The billing batch re-runs: paying a paid transaction | C7: refusal | D7: APX-TOL-01, APX-TOL-03, APX-CORE-05 | E7: Given the nightly batch crashed after e9…0801 was attached and its restart replays the whole file. When it re-sends the same attach with the same Idempotency-Key, then attaches a second, different PaymentRecord to the transaction already paid, then reuses a key with a different body, then attaches one to an id that never existed. Then 200 unchanged for the replay (§15.1; F-TOL-13 fixed), 409 toll-transition-illegal for the different payment (F-TOL-03 fixed), 409 idempotency-conflict for the reused key, and a declared 404. | F7: POST /v1/tolling/transactions/e9000000-0000-4000-8000-000000000801/payment → 200 POST /v1/tolling/transactions/e9000000-0000-4000-8000-000000000801/payment → 409 POST /v1/tolling/transactions/e9000000-0000-4000-8000-000000000801/payment → 409 POST /v1/tolling/transactions/e9000000-0000-4000-8000-0000000008ff/payment → 404 | G7: =IF(F7="",0,LEN(F7)-LEN(SUBSTITUTE(F7,CHAR(10),""))+1)
A8: TOL-07 | B8: Pricing is asynchronous: created first, priced later | C8: lifecycle | D8: APX-TOL-01, APX-TOL-03 | E8: Given an operator whose toll pricing depends on an axle-count classifier that runs a few seconds behind the gantry, outside the APX server. When the bridge posts the passage without pricing, the classifier prices it through POST …/{id}/price, and a retry of the classifier prices it again. Then 201 in created; 200 priced and a status event; 409 toll-transition-illegal for the second price (a later change goes through a dispute), and a read shows the price (§15.1; F-TOL-02 fixed). | F8: POST /v1/tolling/transactions → 201 POST /v1/tolling/transactions/e9000000-0000-4000-8000-000000000803/price → 200 POST /v1/tolling/transactions/e9000000-0000-4000-8000-000000000803/price → 409 GET /v1/tolling/transactions/e9000000-0000-4000-8000-000000000803 → 200 | G8: =IF(F8="",0,LEN(F8)-LEN(SUBSTITUTE(F8,CHAR(10),""))+1)
A9: TOL-08 | B9: 07:52, the passage that was not hers | C9: happy | D9: APX-TOL-02, APX-TOL-01 | E9: Given a vehicle with no transponder passed at 07:52 and the gantry fell back to the plate, reading SYN-9930 at 0.71 confidence; the transaction was created, priced, and billed to the monthly holder of that plate. When she calls ten days later, three hundred miles from the crossing, and the agent opens a dispute naming her as disputedBy. Then 200 with the transaction disputed, the original reads still referenced, the payment still attached, and a status event. Disputes are operator-opened, on the holder's behalf here, and disputedBy names the party (§15.1; F-TOL-08 fixed — APX v1 defines no customer scope). | F9: POST /v1/tolling/transactions → 201 POST /v1/tolling/transactions/e9000000-0000-4000-8000-000000000802/disputes → 200 | G9: =IF(F9="",0,LEN(F9)-LEN(SUBSTITUTE(F9,CHAR(10),""))+1)
A10: TOL-09 | B10: Image review agrees: refunded | C10: happy | D10: APX-TOL-02 | E10: Given the back office compared the gantry image with the vehicle on the holder's account. When it resolves the dispute as refunded with a note. Then 200 with the transaction resolved, dispute.resolvedTime and dispute.resolution set, the history entry naming the reviewer, and the refund itself taken as a Part 13 refund against the original payment. refunded is one of the §15.1 base resolution codes (F-TOL-10 fixed; registry entry pending). | F10: POST /v1/tolling/transactions/e9000000-0000-4000-8000-000000000802/disputes/resolve → 200 | G10: =IF(F10="",0,LEN(F10)-LEN(SUBSTITUTE(F10,CHAR(10),""))+1)
A11: TOL-10 | B11: A stale export tries to reopen the dispute | C11: refusal | D11: APX-TOL-02, APX-CORE-05 | E11: Given the dispute on e9…0802 was resolved on 3 October. When a reconciliation job working from a month-old export posts a new dispute on the same transaction. Then 409 dispute-closed; the transaction stays resolved and the job is told to raise an adjustment instead. Resolved is resolved. | F11: POST /v1/tolling/transactions/e9000000-0000-4000-8000-000000000802/disputes → 409 | G11: =IF(F11="",0,LEN(F11)-LEN(SUBSTITUTE(F11,CHAR(10),""))+1)
A12: TOL-11 | B12: Resolving what is not open | C12: refusal | D12: APX-TOL-02, APX-CORE-05 | E12: Given two operator mistakes. When the back office resolves e9…0802 a second time, and then resolves e9…0801, which was paid and never disputed, and finally resolves an id that does not exist. Then the first is 409 dispute-closed (a closed dispute); the second is 409 toll-transition-illegal, since resolve is allowed from disputed only (§15.1; F-TOL-03 fixed); the third is the declared 404 (F-TOL-06 fixed). | F12: POST /v1/tolling/transactions/e9000000-0000-4000-8000-000000000802/disputes/resolve → 409 POST /v1/tolling/transactions/e9000000-0000-4000-8000-000000000801/disputes/resolve → 409 POST /v1/tolling/transactions/e9000000-0000-4000-8000-0000000008ff/disputes/resolve → 404 | G12: =IF(F12="",0,LEN(F12)-LEN(SUBSTITUTE(F12,CHAR(10),""))+1)
A13: TOL-12 | B13: Two agents dispute the same charge, and one disputes a ghost | C13: refusal | D13: APX-TOL-02, APX-CORE-05 | E13: Given the holder called twice and reached two agents. When the second agent opens a dispute on e9…0802 while the first one is still open (before TOL-09), and a third agent mistypes the id. Then the second dispute is 409 toll-transition-illegal — a dispute opens from priced or paid only (§15.1; F-TOL-03 fixed) — and the mistyped id is the declared 404 (F-TOL-06 fixed). | F13: POST /v1/tolling/transactions/e9000000-0000-4000-8000-000000000802/disputes → 409 POST /v1/tolling/transactions/e9000000-0000-4000-8000-0000000008ff/disputes → 404 | G13: =IF(F13="",0,LEN(F13)-LEN(SUBSTITUTE(F13,CHAR(10),""))+1)
... A25: TOL-24 | B25: The shared responses on the remaining toll routes | C25: edge | D25: APX-CORE-05, APX-CORE-06, APX-CORE-07 | E25: Given the reconciliation job of TOL-20 (throttled, then on an expired token), a BI token with no apx.tolling:manage, and a buggy client. When each hits the routes earlier scenarios did not. Then the shared 401, 403, 429, and 400 responses every secured toll operation declares (Part 12 §12.3; F-TOL-06 fixed). | F25: GET /v1/tolling/transactions/e9000000-0000-4000-8000-000000000801 → 401 GET /v1/tolling/transactions/e9000000-0000-4000-8000-000000000801 → 403 GET /v1/tolling/transactions/e9000000-0000-4000-8000-000000000801 → 429 POST /v1/tolling/transactions/e9000000-0000-4000-8000-000000000803/payment → 400 POST /v1/tolling/transactions/e9000000-0000-4000-8000-000000000803/price → 401 POST /v1/tolling/transactions/e9000000-0000-4000-8000-000000000803/price → 403 POST /v1/tolling/transactions/e9000000-0000-4000-8000-000000000803/price → 429 POST /v1/tolling/transactions/e9000000-0000-4000-8000-000000000812/void → 401 POST /v1/tolling/transactions/e9000000-0000-4000-8000-000000000812/void → 403 POST /v1/tolling/transactions/e9000000-0000-4000-8000-000000000812/void → 429 POST /v1/tolling/transactions/e9000000-0000-4000-8000-000000000804/disputes → 400 POST /v1/tolling/transactions/e9000000-0000-4000-8000-000000000804/disputes → 401 POST /v1/tolling/transactions/e9000000-0000-4000-8000-000000000804/disputes → 403 POST /v1/tolling/transactions/e9000000-0000-4000-8000-000000000804/disputes → 429 POST /v1/tolling/transactions/e9000000-0000-4000-8000-000000000809/disputes/resolve → 400 POST /v1/tolling/transactions/e9000000-0000-4000-8000-000000000809/disputes/resolve → 400 POST /v1/tolling/transactions/e9000000-0000-4000-8000-000000000809/disputes/resolve → 401 POST /v1/tolling/transactions/e9000000-0000-4000-8000-000000000809/disputes/resolve → 403 POST /v1/tolling/transactions/e9000000-0000-4000-8000-000000000809/disputes/resolve → 429 | G25: =IF(F25="",0,LEN(F25)-LEN(SUBSTITUTE(F25,CHAR(10),""))+1)

Sheet apx-valet
A1: ID | B1: Title | C1: Kind | D1: Annex A rows | E1: Scenario (Given / When / Then) | F1: Exchanges (request → status) | G1: Exchange count | H1: Open spec gap
A2: VLT-01 | B2: Drop-off with a scanned condition report; the stay is a Session | C2: happy | D2: APX-VLT-01, APX-VLT-02, APX-VLT-03, APX-VLT-07, APX-VLT-08 | E2: Given a guest pulls up at the hotel valet stand and the attendant's scanning app photographs the car, records a scuff on the rear bumper, and the guest taps to acknowledge. When the app posts the drop-off with an idempotency key. Then 201 with the ticket in dropped, the APDS Session for the stay referenced (never restated), the contact handle masked, imagery as links, and apx.valet.ticket.status.v1 published with the ticket as data. | F2: POST /v1/valet/tickets → 201 | G2: =IF(F2="",0,LEN(F2)-LEN(SUBSTITUTE(F2,CHAR(10),""))+1)
A3: VLT-02 | B3: The scanner retries after a dead spot: same key, same body; then a different body | C3: edge | D3: APX-VLT-01, APX-CORE-05 | E3: Given the 201 from VLT-01 never reached the handheld in the P3 ramp. When it retries with the identical key and body. Then 200 with the ORIGINAL ticket, no second custody record. A second scanner reusing the same key for a different car is 409 idempotency-conflict. | F3: POST /v1/valet/tickets → 200 POST /v1/valet/tickets → 409 | G3: =IF(F3="",0,LEN(F3)-LEN(SUBSTITUTE(F3,CHAR(10),""))+1)
A4: VLT-03 | B4: Broken drop-offs: no key, no drop-off time, a place nobody has | C4: refusal | D4: APX-VLT-01, APX-CORE-05 | E4: Given three misconfigured handhelds. When one omits Idempotency-Key, one sends a ticket with no dropOff, and one names a valet stand that does not exist. Then 400 idempotency-key-required, 400 invalid-request with an errors[] pointer, and 422 reference-unknown (F-VLT-01 and F-VLT-02, fixed: both slugs are now registered and named in the operation's descriptions). | F4: POST /v1/valet/tickets → 400 POST /v1/valet/tickets → 400 POST /v1/valet/tickets → 422 | G4: =IF(F4="",0,LEN(F4)-LEN(SUBSTITUTE(F4,CHAR(10),""))+1)
A5: VLT-04 | B5: Parked: a zone and a hook, then moved to a mapped space | C5: lifecycle | D5: APX-VLT-01 | E5: Given the runner drives V-20419 down to P3. When they record the row and the key hook, and twenty minutes later move it into a mapped Space to free the row. Then the first park transitions dropped → parked, the second updates storage while parked (legal per §22.1 rule 1), and each appends a history entry. A third runner whose screen still shows version 2 sends If-Match: "2" and is refused 409 version-conflict instead of overwriting the move (F-VLT-09, fixed: §22.1 rule 6). A ticket id that does not exist is 404. | F5: POST /v1/valet/tickets/d8000000-0000-4000-8000-000000000419/park → 200 POST /v1/valet/tickets/d8000000-0000-4000-8000-000000000419/park → 200 POST /v1/valet/tickets/d8000000-0000-4000-8000-000000000419/park → 409 POST /v1/valet/tickets/d8000000-0000-4000-8000-0000000000ff/park → 404 | G5: =IF(F5="",0,LEN(F5)-LEN(SUBSTITUTE(F5,CHAR(10),""))+1)
A6: VLT-05 | B6: "CAR" texted two minutes after drop-off: nobody knows where it is yet | C6: refusal | D6: APX-VLT-01, APX-VLT-06 | E6: Given the guest of V-20423 changes plans in the lobby and texts CAR before the runner has parked it. When the SMS gateway calls retrieve on the guest's own token. Then 409 valet-vehicle-not-located, not valet-transition-illegal: the ticket is dropped, the car is somewhere on the ramp, and the gateway texts "give us a moment" rather than an ETA. | F6: POST /v1/valet/tickets/d8000000-0000-4000-8000-000000000423/retrieve → 409 | G6: =IF(F6="",0,LEN(F6)-LEN(SUBSTITUTE(F6,CHAR(10),""))+1)
A7: VLT-06 | B7: "Bring my car" by text: an ETA, a minimized read, two events | C7: happy | D7: APX-VLT-04, APX-VLT-06, APX-VLT-08 | E7: Given two hours later the guest of V-20419 replies CAR to the claim text. When the SMS gateway calls retrieve on the guest's apx.valet:request token. Then 200 with etaMinutes and promisedTime set, in the minimized projection of §22.5 (exactly the listed members: no storage, no key tag, no statusHistory, no requestedBy, no condition report — F-VLT-12, fixed), and the server publishes both apx.valet.retrieval.requested.v1 and apx.valet.ticket.status.v1. The guest texts CAR again a minute later; the repeat is 200 with the same ticket and nothing is republished (F-VLT-13, fixed: §22.3 rule 4). | F7: POST /v1/valet/tickets/d8000000-0000-4000-8000-000000000419/retrieve → 200 POST /v1/valet/tickets/d8000000-0000-4000-8000-000000000419/retrieve → 200 GET /v1/valet/tickets/d8000000-0000-4000-8000-000000000419 → 200 | G7: =IF(F7="",0,LEN(F7)-LEN(SUBSTITUTE(F7,CHAR(10),""))+1)
A8: VLT-07 | B8: The other ways to ask: app, web, voice bot, kiosk, the stand, the call centre | C8: happy | D8: APX-VLT-04, APX-VLT-06 | E8: Given six parked cars and six guests. When one taps the hotel PWA, one uses the web page from the claim link, one tells the voice bot, one uses the lobby kiosk, one walks up to the stand, and one calls the operator's call centre. Then the only difference on the wire is channel — and, for the bot and the call centre, an opaque interaction id. The first three use the customer scope; the last three use apx.valet:manage. | F8: POST /v1/valet/tickets/d8000000-0000-4000-8000-000000000424/retrieve → 200 POST /v1/valet/tickets/d8000000-0000-4000-8000-000000000425/retrieve → 200 POST /v1/valet/tickets/d8000000-0000-4000-8000-000000000426/retrieve → 200 POST /v1/valet/tickets/d8000000-0000-4000-8000-000000000427/retrieve → 200 POST /v1/valet/tickets/d8000000-0000-4000-8000-000000000428/retrieve → 200 POST /v1/valet/tickets/d8000000-0000-4000-8000-000000000429/retrieve → 200 | G8: =IF(F8="",0,LEN(F8)-LEN(SUBSTITUTE(F8,CHAR(10),""))+1)
A9: VLT-08 | B9: A pickup booked for 07:30, and the runner board's horizon | C9: happy | D9: APX-VLT-02, APX-VLT-04 | E9: Given hotel guest M. Adeyemi, on an account, with an AssignedRight as the claim ticket, books the car for 07:30 tomorrow from the PWA at 22:10. When the stand reads the queue with the default horizon, then with a twelve-hour one. Then the scheduled pickup is absent from the first read and present in the second, and the queue is ordered by promisedTime. etaMinutes is 559: whole minutes from 22:10:44 until the promised 07:30, counting down on every read (F-VLT-14, fixed: §22.3 rule 1). The queue for a place that does not exist is 404. | F9: POST /v1/valet/tickets/d8000000-0000-4000-8000-000000000420/retrieve → 200 GET /v1/valet/queue → 200 GET /v1/valet/queue → 200 GET /v1/valet/queue → 404 | G9: =IF(F9="",0,LEN(F9)-LEN(SUBSTITUTE(F9,CHAR(10),""))+1)
A10: VLT-09 | B10: "Actually, another twenty minutes": cancel-retrieval, twice, then once too many | C10: lifecycle | D10: APX-VLT-01, APX-VLT-06 | E10: Given the guest of V-20423 texts WAIT while the request is queued. When the gateway cancels the retrieval. Then the ticket returns to parked with the reason recorded. The runner had already picked it up the second time the guest asked; cancelling from retrieving is also legal and the car goes back. Cancelling when nothing is requested is 409 valet-transition-illegal. | F10: POST /v1/valet/tickets/d8000000-0000-4000-8000-000000000423/cancel-retrieval → 200 POST /v1/valet/tickets/d8000000-0000-4000-8000-000000000423/cancel-retrieval → 200 POST /v1/valet/tickets/d8000000-0000-4000-8000-000000000423/cancel-retrieval → 409 | G10: =IF(F10="",0,LEN(F10)-LEN(SUBSTITUTE(F10,CHAR(10),""))+1)
A11: VLT-10 | B11: The runner picks it up, stages it at the front entrance | C11: lifecycle | D11: APX-VLT-01, APX-VLT-04, APX-VLT-08 | E11: Given V-20419 is requested. When the runner's app records the pickup with POST …/pickup (F-VLT-05, fixed: §22.1 rule 2) and then stages the car at lane b2…0051. Then pickup answers 200 in retrieving with retrievingBy, the status event shows the same, stage answers 200 with stagingLane and stagedTime set and etaMinutes at 0, and the guest's contact channel is notified. A pickup on a car nobody asked for is 409; on an id nobody has, 404. A staged car the guest no longer wants is re-parked with park (F-VLT-06, fixed: §22.1 rule 1); cancel-retrieval on it is still 409. | F11: POST /v1/valet/tickets/d8000000-0000-4000-8000-000000000419/pickup → 200 POST /v1/valet/tickets/d8000000-0000-4000-8000-000000000423/pickup → 409 POST /v1/valet/tickets/d8000000-0000-4000-8000-0000000000ff/pickup → 404 POST /v1/valet/tickets/d8000000-0000-4000-8000-000000000419/stage → 200 POST /v1/valet/tickets/d8000000-0000-4000-8000-000000000429/cancel-retrieval → 409 POST /v1/valet/tickets/d8000000-0000-4000-8000-000000000429/park → 200 | G11: =IF(F11="",0,LEN(F11)-LEN(SUBSTITUTE(F11,CHAR(10),""))+1)
A12: VLT-11 | B12: Verified by code, handed back, one mile on the clock; closed when the stay settles | C12: happy | D12: APX-VLT-02, APX-VLT-05, APX-VLT-08 | E12: Given V-20419 is staged and the guest shows the claim code at the stand. When the attendant's app verifies the code and records the handback condition and mileage. Then 200 with the ticket in handedBack, verificationValue absent from the record, the handback report alongside the drop-off one, and handback.mileage one mile over dropOff.mileage. The Session is paid at the stand through the ordinary payment surface; closed follows server-side, announced by the status event. | F12: POST /v1/valet/tickets/d8000000-0000-4000-8000-000000000419/handback → 200 | G12: =IF(F12="",0,LEN(F12)-LEN(SUBSTITUTE(F12,CHAR(10),""))+1)
A13: VLT-12 | B13: The wrong claimant: verification fails, and the audit keeps it | C13: refusal | D13: APX-VLT-05 | E13: Given V-20429 is staged and someone presents a code that does not match. When the attendant's app submits the handback. Then 403 valet-verification-failed, the car stays staged, and the attempt — method, actor, time — is appended to statusHistory[] without the value presented. The guest then produces ID, and the second handback succeeds. | F13: POST /v1/valet/tickets/d8000000-0000-4000-8000-000000000429/handback → 403 GET /v1/valet/tickets/d8000000-0000-4000-8000-000000000429 → 200 POST /v1/valet/tickets/d8000000-0000-4000-8000-000000000429/handback → 200 | G13: =IF(F13="",0,LEN(F13)-LEN(SUBSTITUTE(F13,CHAR(10),""))+1)
... A26: VLT-25 | B26: Malformed transition bodies: every action route says which field | C26: refusal | D26: APX-VLT-01, APX-CORE-05 | E26: Given a third-party runner app built against a draft of the API. When it sends each action route a body that fails its schema — a numeric zone, a channel nobody defined, a cancel with no reason, a stage with no lane, a handback with no verification method, a numeric runner id, a cancel with no reason, a damage entry with no area. Then 400 invalid-request on every one, with an errors[] pointer to the offending member (Part 12 §12.4); nothing changes on V-20431. | F26: POST /v1/valet/tickets/d8000000-0000-4000-8000-000000000431/park → 400 POST /v1/valet/tickets/d8000000-0000-4000-8000-000000000431/retrieve → 400 POST /v1/valet/tickets/d8000000-0000-4000-8000-000000000431/cancel-retrieval → 400 POST /v1/valet/tickets/d8000000-0000-4000-8000-000000000431/stage → 400 POST /v1/valet/tickets/d8000000-0000-4000-8000-000000000431/handback → 400 POST /v1/valet/tickets/d8000000-0000-4000-8000-000000000431/pickup → 400 POST /v1/valet/tickets/d8000000-0000-4000-8000-000000000431/cancel → 400 POST /v1/valet/tickets/d8000000-0000-4000-8000-000000000431/condition → 400 | G26: =IF(F26="",0,LEN(F26)-LEN(SUBSTITUTE(F26,CHAR(10),""))+1)

Sheet apx-validations
A1: ID | B1: Title | C1: Kind | D1: Annex A rows | E1: Scenario (Given / When / Then) | F1: Exchanges (request → status) | G1: Exchange count | H1: Open spec gap
A2: VAL-01 | B2: Enrol two merchants; the cinema brings an extension | C2: happy | D2: APX-VAL-01, APX-VAL-08, APX-CORE-04 | E2: Given the back office signs Harbor Bistro and Lakeside Cinema for Lakeside Garage on the first of the month. When it enrols each with an idempotency key — the cinema's contract carries a happy-hour clause the closed rule set cannot express, so it rides in extensions. Then both come back 201 in active with version: 1 and one history entry, apx.validations.program.status.v1 fires for each, and a later read of the cinema returns the extension key untouched. | F2: POST /v1/validations/programs → 201 POST /v1/validations/programs → 201 GET /v1/validations/programs/e5000000-0000-4000-8000-000000000002 → 200 | G2: =IF(F2="",0,LEN(F2)-LEN(SUBSTITUTE(F2,CHAR(10),""))+1)
A3: VAL-02 | B3: The back office retries the enrolment, then reuses the key by mistake | C3: edge | D3: APX-VAL-01, APX-CORE-05 | E3: Given the 201 for Harbor Bistro never reached the back-office client. When it retries with the identical key and body, then a copy-paste error sends the cinema's body under the bistro's key, and a third client forgets the header altogether. Then 200 with the program's current representation (Part 4 §4.2a; no second enrolment), 409 idempotency-conflict, and 400 idempotency-key-required. | F3: POST /v1/validations/programs → 200 POST /v1/validations/programs → 409 POST /v1/validations/programs → 400 | G3: =IF(F3="",0,LEN(F3)-LEN(SUBSTITUTE(F3,CHAR(10),""))+1)
A4: VAL-03 | B4: Enrolment refused: a benefit that is two things, and a merchant nobody knows | C4: refusal | D4: APX-VAL-01 | E4: Given a gym contract typed up in a hurry. When the back office sends a benefit with both amount and duration, and then one whose provider is an organisation the server has never heard of. Then 422 request-unprocessable and 422 reference-unknown, the two types the route's 422 description now names (F-VAL-02 fixed). The ValidationBenefit schema still accepts the two-headed benefit: adding a oneOf would narrow a request body clients already send, so the "exactly one" rule is stated in the schema description and §20.1 and enforced as the 422 instead. | F4: POST /v1/validations/programs → 422 POST /v1/validations/programs → 422 | G4: =IF(F4="",0,LEN(F4)-LEN(SUBSTITUTE(F4,CHAR(10),""))+1)
A5: VAL-04 | B5: The provider list is the program list, and the agent's validation lands in the ledger | C5: happy | D5: APX-VAL-02, APX-VAL-04 | E5: Given three active programs at Lakeside (the fitness program was enrolled correctly after VAL-03). When a call-center agent asks Part 6 for the place's providers and applies the cinema's validation to ticket T-1001 at exit lane 2 with applyValidation. Then the provider list is exactly the active programs, each row carrying program; the command is accepted; and the ledger holds a ValidationRedemption with channel: callCenter and command set, findable from the command's id with ?command= (F-VAL-09 fixed on the redemption side; the reverse link on Command waits on F-CTL-02). The fitness row's percentage still has no home in ValidationProvider.benefit, which the control class owns (F-VAL-10, open for the control group). | F5: GET /v1/validations/providers → 200 POST /v1/commands → 202 GET /v1/validations/redemptions → 200 | G5: =IF(F5="",0,LEN(F5)-LEN(SUBSTITUTE(F5,CHAR(10),""))+1)
A6: VAL-05 | B6: Projector fault: suspend the cinema for two days, then resume | C6: lifecycle | D6: APX-VAL-01, APX-VAL-02, APX-VAL-08 | E6: Given the cinema closes for a projector repair and does not want stamps honoured meanwhile. When the back office PUTs the program to suspended with version: 1, checks the Part 6 provider list, and two days later PUTs it back to active with version: 2. Then each PUT returns the next version with a new history entry, the extension rides along untouched, the provider list omits the cinema while suspended, and apx.validations.program.status.v1 fires on both transitions. | F6: PUT /v1/validations/programs/e5000000-0000-4000-8000-000000000002 → 200 GET /v1/validations/providers → 200 PUT /v1/validations/programs/e5000000-0000-4000-8000-000000000002 → 200 | G6: =IF(F6="",0,LEN(F6)-LEN(SUBSTITUTE(F6,CHAR(10),""))+1)
A7: VAL-06 | B7: Two back-office users edit the bistro at once | C7: refusal | D7: APX-VAL-01, APX-CORE-03 | E7: Given two users both read the bistro program at version: 1; the first raises maxPerDay and wins. When the second sends a PUT with If-Match: "1" (and the same version: 1 echoed in the body) to change the billing cycle, and then a script PUTs a body with no benefit. Then 409 version-conflict — nothing is written, and the loser re-reads before retrying — and 400 invalid-request. The route declares the shared IfMatch parameter and Part 4 §4.2a makes the readOnly body version the equivalent precondition, so both carriers are conformant (F-VAL-11 fixed; the PUT's 400 closes the F-VAL-12 part for this route). | F7: PUT /v1/validations/programs/e5000000-0000-4000-8000-000000000001 → 409 PUT /v1/validations/programs/e5000000-0000-4000-8000-000000000001 → 400 | G7: =IF(F7="",0,LEN(F7)-LEN(SUBSTITUTE(F7,CHAR(10),""))+1)
A8: VAL-07 | B8: The gym leaves: ended is terminal | C8: lifecycle | D8: APX-VAL-01, APX-VAL-08 | E8: Given Lakeside Fitness closes at the end of September. When the back office ends the program, and a month later someone tries to resume it, and the gym's app tries to issue digital codes against it. Then the end transition returns 200 in ended and publishes apx.validations.program.status.v1; the resume is 422 program-not-active; and the issuance is 422 program-not-active. | F8: PUT /v1/validations/programs/e5000000-0000-4000-8000-000000000004 → 200 PUT /v1/validations/programs/e5000000-0000-4000-8000-000000000004 → 422 POST /v1/validations/programs/e5000000-0000-4000-8000-000000000004/issuances → 422 | G8: =IF(F8="",0,LEN(F8)-LEN(SUBSTITUTE(F8,CHAR(10),""))+1)
A9: VAL-08 | B9: The bistro prints a sheet of QR codes, and the print job retries | C9: happy | D9: APX-VAL-03 | E9: Given Harbor Bistro's iPad on the merchant scope (apx.validations:redeem, apx_org = a2…0077). When it issues 50 QR codes, the print spooler retries with the same key, and the back office later lists the program's batches. Then 201 with codes[] (abridged here to three) and validTo defaulted from the one-day validityWindow; the replay is 200 with the batch's current representation and no codes; the list never shows codes. A reused key with a different quantity is 409, and a batch without a key is 400. The first two bodies are the public scenario 18 shape, which now validates: the create body is ValidationIssuanceRequest, where program is optional because the path names it (F-VAL-04 fixed). The later bodies repeat it, which is still allowed when it matches the path. | F9: POST /v1/validations/programs/e5000000-0000-4000-8000-000000000001/issuances → 201 POST /v1/validations/programs/e5000000-0000-4000-8000-000000000001/issuances → 200 POST /v1/validations/programs/e5000000-0000-4000-8000-000000000001/issuances → 409 POST /v1/validations/programs/e5000000-0000-4000-8000-000000000001/issuances → 400 GET /v1/validations/programs/e5000000-0000-4000-8000-000000000001/issuances → 200 | G9: =IF(F9="",0,LEN(F9)-LEN(SUBSTITUTE(F9,CHAR(10),""))+1)
A10: VAL-09 | B10: A method the program never agreed to, and stamps for the cinema | C10: refusal | D10: APX-VAL-03 | E10: Given the bistro's program allows qrCode only. When its iPad asks for a stamp batch. Then 422 request-unprocessable, which the route's 422 description now names for "method not in issuanceMethods" (F-VAL-03 fixed). The cinema, whose program does allow stamps, orders 500: 201 with no codes[], because stamps are physical stock counted for billing. | F10: POST /v1/validations/programs/e5000000-0000-4000-8000-000000000001/issuances → 422 POST /v1/validations/programs/e5000000-0000-4000-8000-000000000002/issuances → 201 | G10: =IF(F10="",0,LEN(F10)-LEN(SUBSTITUTE(F10,CHAR(10),""))+1)
A11: VAL-10 | B11: A guest scans a code at the pay station | C11: happy | D11: APX-VAL-03, APX-VAL-04, APX-VAL-08 | E11: Given ticket T-2210 owes $9.00 and the guest has a bistro QR code. When pay station 3 (operator token) checks the code, then redeems it with an idempotency key, then checks it again. Then the first check is 200 valid with the benefit to display; the redemption is 201 with validationId materialized on the APDS session and amountReduced at the actual $6.00 the two hours were worth; apx.validations.redeemed.v1 fires; and the second check shows redeemed pointing at the redemption. | F11: GET /v1/validations/instruments/HB-7Q2M-K9X4-3TPD → 200 POST /v1/validations/redemptions → 201 GET /v1/validations/instruments/HB-7Q2M-K9X4-3TPD → 200 | G11: =IF(F11="",0,LEN(F11)-LEN(SUBSTITUTE(F11,CHAR(10),""))+1)
A12: VAL-11 | B12: The pay station's network hiccups mid-redemption | C12: edge | D12: APX-VAL-04, APX-CORE-05 | E12: Given the 201 from VAL-10 was lost on the wire. When the pay station retries with the same key and body; then a firmware bug reuses that key for the next guest; then a third redemption arrives with no key. Then 200 with the redemption's current representation (the code is not consumed twice, the ticket not reduced twice), 409 idempotency-conflict, and 400 idempotency-key-required. | F12: POST /v1/validations/redemptions → 200 POST /v1/validations/redemptions → 409 POST /v1/validations/redemptions → 400 | G12: =IF(F12="",0,LEN(F12)-LEN(SUBSTITUTE(F12,CHAR(10),""))+1)
A13: VAL-12 | B13: Codes that are not good: unknown, expired, used, void, and missing | C13: refusal | D13: APX-VAL-03, APX-VAL-04 | E13: Given five guests at pay station 3 over one evening. When one presents a code that was never issued, one a code from last week's sheet, one the code already used on T-2210, one a code from a sheet the bistro reported stolen, and one a bistro validation with no code at all. Then the unknown code is 404 on lookup and 422 instrument-invalid on redemption; the others are 200 on lookup with their status, and 422 instrument-invalid on redemption. The stolen sheet was voided through POST …/issuances/{issuanceId}/void earlier that evening (VAL-25; F-VAL-05 fixed). | F13: GET /v1/validations/instruments/HB-ZZZZ-ZZZZ-ZZZZ → 404 POST /v1/validations/redemptions → 422 GET /v1/validations/instruments/HB-E1X9-P4RD-0OLD → 200 POST /v1/validations/redemptions → 422 POST /v1/validations/redemptions → 422 GET /v1/validations/instruments/HB-S7K2-QW4N-8HGV → 200 POST /v1/validations/redemptions → 422 POST /v1/validations/redemptions → 422 | G13: =IF(F13="",0,LEN(F13)-LEN(SUBSTITUTE(F13,CHAR(10),""))+1)
... A26: VAL-25 | B26: The stolen sheet: void a batch, then one leaked code | C26: lifecycle | D26: APX-VAL-03, APX-VAL-06 | E26: Given at 19:30 on 12 September a server at Harbor Bistro reports the second sheet of the evening (e6…0005, 50 QR codes, two already redeemed) stolen from the host stand, and a photo of one code from sheet 3 (HB-L3AK-ED01-QR7Z) turns up on social media. When the bistro's iPad voids the batch, its retry voids it again, the back office voids the leaked code, tries to void the code already redeemed on T-2210 and one that was never issued, the iPad tries to void the cinema's stamp roll, two scripts send voids with no reason, a BI token tries both routes, and an expired token and a flooding job hit them. Then 200 void with voidDetail.voidedCount: 48 (the two redeemed codes stand); 200 unchanged; 200 on the single code; 422 instrument-invalid for the redeemed one; 404 for the unknown code and for another provider's batch (§20.5); 400 invalid-request twice; 403 insufficient-scope twice; 401 twice; 429 twice. VAL-12 then shows a code from the voided sheet refused at the pay station (F-VAL-05 fixed). | F26: POST /v1/validations/programs/e5000000-0000-4000-8000-000000000001/issuances/e6000000-0000-4000-8000-000000000005/void → 200 POST /v1/validations/programs/e5000000-0000-4000-8000-000000000001/issuances/e6000000-0000-4000-8000-000000000005/void → 200 POST /v1/validations/instruments/HB-L3AK-ED01-QR7Z/void → 200 POST /v1/validations/instruments/HB-7Q2M-K9X4-3TPD/void → 422 POST /v1/validations/instruments/HB-ZZZZ-ZZZZ-ZZZZ/void → 404 POST /v1/validations/programs/e5000000-0000-4000-8000-000000000002/issuances/e6000000-0000-4000-8000-000000000004/void → 404 POST /v1/validations/programs/e5000000-0000-4000-8000-000000000001/issuances/e6000000-0000-4000-8000-000000000003/void → 400 POST /v1/validations/instruments/HB-P0V3-E7HS-M2QY/void → 400 POST /v1/validations/programs/e5000000-0000-4000-8000-000000000001/issuances/e6000000-0000-4000-8000-000000000003/void → 403 POST /v1/validations/instruments/HB-P0V3-E7HS-M2QY/void → 403 POST /v1/validations/programs/e5000000-0000-4000-8000-000000000001/issuances/e6000000-0000-4000-8000-000000000003/void → 401 POST /v1/validations/instruments/HB-P0V3-E7HS-M2QY/void → 401 POST /v1/validations/programs/e5000000-0000-4000-8000-000000000001/issuances/e6000000-0000-4000-8000-000000000003/void → 429 POST /v1/validations/instruments/HB-P0V3-E7HS-M2QY/void → 429 | G26: =IF(F26="",0,LEN(F26)-LEN(SUBSTITUTE(F26,CHAR(10),""))+1)

Sheet apx-violations
A1: ID | B1: Title | C1: Kind | D1: Annex A rows | E1: Scenario (Given / When / Then) | F1: Exchanges (request → status) | G1: Exchange count | H1: Open spec gap
A2: VIO-01 | B2: Handheld screen-pop: entitled by a permit bound to the garage | C2: happy | D2: APX-VIO-06 | E2: Given officer Okafor walks Level 2 with a handheld that asks one question per plate. When it asks about SYN-1234, whose monthly permit is bound to the garage root, an ancestor of Level 2. Then entitled: true with the ancestor-bound right as the valid basis and the last read; nothing is created. The same question with an explicit credentialType and at is answered for that instant. | F2: GET /v1/enforcement/eligibility → 200 GET /v1/enforcement/eligibility → 200 | G2: =IF(F2="",0,LEN(F2)-LEN(SUBSTITUTE(F2,CHAR(10),""))+1)
A3: VIO-02 | B3: Not entitled: wrong level, early arrival, and a place that does not exist | C3: happy | D3: APX-VIO-06 | E3: Given SYN-8820 holds a Level 3 permit and is parked on Level 2, and SYN-7007 has a reservation on Level 2 starting at noon. When the handheld asks at 10:14, and again for SYN-7007 at 11:30 in the past. Then wrongPlace and notYetValid bases with advisory suggestedViolationType values the officer is free to overrule; a place id nobody has is 404. | F3: GET /v1/enforcement/eligibility → 200 GET /v1/enforcement/eligibility → 200 GET /v1/enforcement/eligibility → 404 | G3: =IF(F3="",0,LEN(F3)-LEN(SUBSTITUTE(F3,CHAR(10),""))+1)
A4: VIO-03 | B4: The LPR van finds an overstay in Lot C | C4: happy | D4: APX-VIO-01, APX-VIO-08, APX-VIO-09 | E4: Given the van's 09:31 read of SYN-4471 is already an APDS Observation, and the pay-by-plate session ended at 09:05. When the pipeline records the violation with the observation, an image link, and the location copied from the Observation. Then 201 in detected with the eligibility check the server ran at creation stored on the record, and apx.violations.detected.v1 is published with the Violation as data. | F4: POST /v1/violations → 201 | G4: =IF(F4="",0,LEN(F4)-LEN(SUBSTITUTE(F4,CHAR(10),""))+1)
A5: VIO-04 | B5: The van uploads the same batch twice, then a bug reuses a key | C5: edge | D5: APX-VIO-01 | E5: Given the van lost connectivity after the 201 in VIO-03. When it retries with the identical key and body. Then 200 with the ORIGINAL violation, whatever state it has reached; no second record. A later upload that reuses the key for a different plate is 409 idempotency-conflict and records nothing. | F5: POST /v1/violations → 200 POST /v1/violations → 409 | G5: =IF(F5="",0,LEN(F5)-LEN(SUBSTITUTE(F5,CHAR(10),""))+1)
A6: VIO-05 | B6: Malformed detections: no key, no detection, latitude first, unknown type, unknown place | C6: refusal | D6: APX-VIO-01, APX-VIO-09 | E6: Given five broken integrations. When one omits Idempotency-Key, one sends no detection, one sends coordinates latitude-first (the second element, −87.62, is outside −90..90), one uses a violationType in nobody's registry, and one names a place that does not exist. Then 400 idempotency-key-required, 400 invalid-request twice (with errors[] naming the member), and 422 reference-unknown twice — the types the route's 400 and 422 descriptions now name (F-VIO-02, F-VIO-03 fixed). | F6: POST /v1/violations → 400 POST /v1/violations → 400 POST /v1/violations → 400 POST /v1/violations → 422 POST /v1/violations → 422 | G6: =IF(F6="",0,LEN(F6)-LEN(SUBSTITUTE(F6,CHAR(10),""))+1)
A7: VIO-06 | B7: The pipeline reads a monthly permit holder: recorded, and dismissed | C7: happy | D7: APX-VIO-01 | E7: Given the van also reads SYN-1234 in Lot C, and the garage-wide monthly permit covers Lot C. When the pipeline submits it anyway (its pre-filter is off). Then 201, but in dismissed, with the valid basis on the record: the audit shows what was checked, and the queue's false-positive rate is measurable. | F7: POST /v1/violations → 201 | G7: =IF(F7="",0,LEN(F7)-LEN(SUBSTITUTE(F7,CHAR(10),""))+1)
A8: VIO-07 | B8: Guided: the officer records the candidate, then confirms with a corrected type | C8: happy | D8: APX-VIO-03, APX-VIO-08, APX-VIO-09 | E8: Given the screen-pop in VIO-02 said wrongPlace for SYN-8820. When the handheld records a guided detection with the officer's own position, and on site the officer finds the car in the accessible bay and confirms with violationType: restrictedSpace. Then 201 detected, then 200 confirmed carrying the officer's correction, and apx.violations.status.v1 is published for the review. location is now described as *modelled on* the APDS Observation Location — observerLocation optional, accuracyMetres added — so the handheld's body is conformant as written (F-VIO-16 fixed). | F8: POST /v1/violations → 201 POST /v1/violations/d3000000-0000-4000-8000-000000000003/review → 200 | G8: =IF(F8="",0,LEN(F8)-LEN(SUBSTITUTE(F8,CHAR(10),""))+1)
A9: VIO-08 | B9: Skipping review: a guided candidate, and an automated one where the policy forbids it | C9: refusal | D9: APX-VIO-03 | E9: Given a guided detection of SYN-6102 in Lot C still in detected, and an automated bay-camera detection of a cloned permit on Level 2, where the garage policy in force says unreviewedIssuance.permitted: false. When the pipeline first reads the effective policy, then an over-eager integration issues both straight away. Then the pipeline can see the refusal coming from …/policies/effective; 409 violation-not-issuable twice; issuing an id that does not exist is 404 (F-VIO-04 fixed: the rule is on the policy resource). | F9: GET /v1/enforcement/policies/effective → 200 POST /v1/violations → 201 POST /v1/violations/d3000000-0000-4000-8000-000000000004/issue → 409 POST /v1/violations → 201 POST /v1/violations/d3000000-0000-4000-8000-000000000005/issue → 409 POST /v1/violations/d3000000-0000-4000-8000-0000000000ff/issue → 404 | G9: =IF(F9="",0,LEN(F9)-LEN(SUBSTITUTE(F9,CHAR(10),""))+1)
A10: VIO-09 | B10: Dismissed on site, reviewed twice, dismissed without a reason | C10: refusal | D10: APX-VIO-02, APX-VIO-03 | E10: Given the handheld read SYN-2211 on Level 2 but the plate is SYN-2271 with a valid permit. When the officer dismisses with plateMisread, then the handheld's retry reviews the same record again, and a back-office user dismisses the Level 2 permit case with no reason. Then 200 dismissed (never deleted), 409 violation-transition-illegal, and 400 invalid-request for the missing reason — the rule is in the schema's reason description and §19.1 rule 1, and review declares the 400 (F-VIO-05 fixed; stated in prose rather than an if/then, which would narrow an existing request body). Reviewing an unknown id is 404. | F10: POST /v1/violations → 201 POST /v1/violations/d3000000-0000-4000-8000-000000000006/review → 200 POST /v1/violations/d3000000-0000-4000-8000-000000000006/review → 409 POST /v1/violations/d3000000-0000-4000-8000-000000000005/review → 400 POST /v1/violations/d3000000-0000-4000-8000-0000000000ff/review → 404 | G10: =IF(F10="",0,LEN(F10)-LEN(SUBSTITUTE(F10,CHAR(10),""))+1)
A11: VIO-10 | B11: Unreviewed automated issuance by mail, policy and signage frozen on | C11: happy | D11: APX-VIO-03, APX-VIO-08, APX-VIO-10, APX-VIO-12 | E11: Given the VIO-03 overstay in Lot C, and Lot C policy d4…0001 (unreviewedIssuance permitted at confidence ≥ 0.9; mail allowed for automated detections within 14 days, with one observation, one image, and a position). When the pipeline issues a $35 mailed notice. Then 200 issued, with the policy version, the entrance sign in force at detectedTime, the unpaid fee ($18.00) and the resulting cap (2× = $36.00) as unpaidAmount/capAmount, and the first amountHistory entry frozen onto the record, and apx.violations.issued.v1 published (F-VIO-06 fixed). | F11: POST /v1/violations/d3000000-0000-4000-8000-000000000001/issue → 200 | G11: =IF(F11="",0,LEN(F11)-LEN(SUBSTITUTE(F11,CHAR(10),""))+1)
A12: VIO-11 | B12: A guided notice by mail, then above the cap, then lawful on the windshield | C12: refusal | D12: APX-VIO-10, APX-VIO-12 | E12: Given the guided Lot C detection d3…0004 from VIO-08. When the officer confirms it, the handheld defaults to mail, then retries on the windshield at $40 against an $18 unpaid fee, then sends a body with no amount, then at $35. Then 422 delivery-method-not-permitted (mail is lawful only for camera detections), 422 penalty-exceeds-cap (2× = $36, onExceed: refuse), 400 invalid-request, and finally 200 issued with the policy, sign, unpaidAmount, and capAmount frozen. | F12: POST /v1/violations/d3000000-0000-4000-8000-000000000004/review → 200 POST /v1/violations/d3000000-0000-4000-8000-000000000004/issue → 422 POST /v1/violations/d3000000-0000-4000-8000-000000000004/issue → 422 POST /v1/violations/d3000000-0000-4000-8000-000000000004/issue → 400 POST /v1/violations/d3000000-0000-4000-8000-000000000004/issue → 200 | G12: =IF(F12="",0,LEN(F12)-LEN(SUBSTITUTE(F12,CHAR(10),""))+1)
A13: VIO-12 | B13: Too late, and not enough evidence | C13: refusal | D13: APX-VIO-10 | E13: Given two automated Lot C detections the back office only now gets to: d3…0007, a maximum-stay overstay detected sixteen days ago, and d3…0008, a street-cleaning read whose camera sent no position. When both are issued by mail. Then 422 notice-deadline-passed (14 days) and 422 delivery-method-not-permitted with detail naming the missing evidence. | F13: POST /v1/violations/d3000000-0000-4000-8000-000000000007/issue → 422 POST /v1/violations/d3000000-0000-4000-8000-000000000008/issue → 422 | G13: =IF(F13="",0,LEN(F13)-LEN(SUBSTITUTE(F13,CHAR(10),""))+1)
... A30: VIO-29 | B30: Pay now, contest later: a reduced appeal refunds the difference; a paid notice voided in error | C30: lifecycle | D30: APX-VIO-02, APX-VIO-04, APX-VIO-05 | E30: Given d3…0021, an automated Lot C notice of $35 issued 2026-09-24 and paid on 2026-09-26 (PaymentRecord d9…0004) by a driver who wanted to stop any late fee; and d3…0022, a $35 notice paid the same day that the operator later finds was issued against a misread plate. When the driver appeals d3…0021 on day 5, inside the 21-day window; the reviewer reduces it to $20 and the portal refunds $15 through Part 13 (d9…0005); and the supervisor voids d3…0022 with the full refund d9…0006. Then appealed with appeal.openedFrom: paid, back to paid at $20 with appeal.refund recorded, and voided from paid with the refund linked. This is the §19.6 path that was unreachable before (F-VIO-13 fixed) and the paid → voided transition (F-VIO-10). | F30: POST /v1/violations/d3000000-0000-4000-8000-000000000021/appeals → 200 POST /v1/violations/d3000000-0000-4000-8000-000000000021/appeals/resolve → 200 POST /v1/violations/d3000000-0000-4000-8000-000000000022/void → 200 | G30: =IF(F30="",0,LEN(F30)-LEN(SUBSTITUTE(F30,CHAR(10),""))+1)
